{
  "metadata": {
    "version": 1,
    "timestamp_ms": 1770603169985,
    "asset": "HYPE",
    "session_duration_s": 3600.1754759
  },
  "learned_params": {
    "alpha_touch": {
      "name": "alpha_touch",
      "family": "Beta",
      "prior_mean": 0.25,
      "prior_strength": 8.0,
      "posterior_param1": 63.0,
      "posterior_param2": 66.0,
      "n_observations": 121,
      "sum_x": 0.0,
      "sum_x2": 0.0
    },
    "gamma_base": {
      "name": "gamma_base",
      "family": "Gamma",
      "prior_mean": 0.15,
      "prior_strength": 3.0,
      "posterior_param1": 3.0,
      "posterior_param2": 20.0,
      "n_observations": 0,
      "sum_x": 0.0,
      "sum_x2": 0.0
    },
    "spread_floor_bps": {
      "name": "spread_floor_bps",
      "family": "Normal",
      "prior_mean": 5.0,
      "prior_strength": 0.25,
      "posterior_param1": 5.0,
      "posterior_param2": 4.0,
      "n_observations": 0,
      "sum_x": 0.0,
      "sum_x2": 0.0
    },
    "proactive_skew_sensitivity": {
      "name": "proactive_skew_sensitivity",
      "family": "Normal",
      "prior_mean": 2.0,
      "prior_strength": 4.0,
      "posterior_param1": 2.0,
      "posterior_param2": 0.25,
      "n_observations": 0,
      "sum_x": 0.0,
      "sum_x2": 0.0
    },
    "quote_gate_edge_threshold": {
      "name": "quote_gate_edge_threshold",
      "family": "Beta",
      "prior_mean": 0.15,
      "prior_strength": 100.0,
      "posterior_param1": 15.0,
      "posterior_param2": 85.0,
      "n_observations": 0,
      "sum_x": 0.0,
      "sum_x2": 0.0
    },
    "toxic_hour_gamma_mult": {
      "name": "toxic_hour_gamma_mult",
      "family": "LogNormal",
      "prior_mean": 2.0,
      "prior_strength": 3.4064542452769913,
      "posterior_param1": 0.6500583324394191,
      "posterior_param2": 0.08617769624105241,
      "n_observations": 0,
      "sum_x": 0.0,
      "sum_x2": 0.0
    },
    "predictive_bias_sensitivity": {
      "name": "predictive_bias_sensitivity",
      "family": "Normal",
      "prior_mean": 2.0,
      "prior_strength": 1.0,
      "posterior_param1": 2.0,
      "posterior_param2": 1.0,
      "n_observations": 0,
      "sum_x": 0.0,
      "sum_x2": 0.0
    },
    "max_daily_loss_fraction": {
      "name": "max_daily_loss_fraction",
      "family": "Beta",
      "prior_mean": 0.02,
      "prior_strength": 50.0,
      "posterior_param1": 1.0,
      "posterior_param2": 49.0,
      "n_observations": 0,
      "sum_x": 0.0,
      "sum_x2": 0.0
    },
    "max_drawdown": {
      "name": "max_drawdown",
      "family": "Beta",
      "prior_mean": 0.05,
      "prior_strength": 20.0,
      "posterior_param1": 1.0,
      "posterior_param2": 19.0,
      "n_observations": 0,
      "sum_x": 0.0,
      "sum_x2": 0.0
    },
    "cascade_oi_threshold": {
      "name": "cascade_oi_threshold",
      "family": "Beta",
      "prior_mean": 0.02,
      "prior_strength": 100.0,
      "posterior_param1": 2.0,
      "posterior_param2": 98.0,
      "n_observations": 0,
      "sum_x": 0.0,
      "sum_x2": 0.0
    },
    "bocpd_hazard_rate": {
      "name": "bocpd_hazard_rate",
      "family": "Gamma",
      "prior_mean": 0.004,
      "prior_strength": 1.0,
      "posterior_param1": 1.0,
      "posterior_param2": 250.0,
      "n_observations": 0,
      "sum_x": 0.0,
      "sum_x2": 0.0
    },
    "bocpd_threshold": {
      "name": "bocpd_threshold",
      "family": "Beta",
      "prior_mean": 0.7,
      "prior_strength": 10.0,
      "posterior_param1": 7.0,
      "posterior_param2": 3.0000000000000004,
      "n_observations": 0,
      "sum_x": 0.0,
      "sum_x2": 0.0
    },
    "quote_latch_threshold_bps": {
      "name": "quote_latch_threshold_bps",
      "family": "Normal",
      "prior_mean": 2.5,
      "prior_strength": 1.0,
      "posterior_param1": 2.5,
      "posterior_param2": 1.0,
      "n_observations": 0,
      "sum_x": 0.0,
      "sum_x2": 0.0
    },
    "kappa": {
      "name": "kappa",
      "family": "Gamma",
      "prior_mean": 2000.0,
      "prior_strength": 4.0,
      "posterior_param1": 6388.0,
      "posterior_param2": 23.280842481008275,
      "n_observations": 95,
      "sum_x": 6384.0,
      "sum_x2": 0.0
    },
    "hawkes_mu": {
      "name": "hawkes_mu",
      "family": "Gamma",
      "prior_mean": 0.5,
      "prior_strength": 5.0,
      "posterior_param1": 5.0,
      "posterior_param2": 10.0,
      "n_observations": 0,
      "sum_x": 0.0,
      "sum_x2": 0.0
    },
    "hawkes_alpha": {
      "name": "hawkes_alpha",
      "family": "Beta",
      "prior_mean": 0.3,
      "prior_strength": 10.0,
      "posterior_param1": 3.0,
      "posterior_param2": 7.0,
      "n_observations": 0,
      "sum_x": 0.0,
      "sum_x2": 0.0
    },
    "hawkes_beta": {
      "name": "hawkes_beta",
      "family": "Gamma",
      "prior_mean": 0.1,
      "prior_strength": 1.0,
      "posterior_param1": 1.0,
      "posterior_param2": 10.0,
      "n_observations": 0,
      "sum_x": 0.0,
      "sum_x2": 0.0
    },
    "kappa_ewma_alpha": {
      "name": "kappa_ewma_alpha",
      "family": "Beta",
      "prior_mean": 0.9,
      "prior_strength": 100.0,
      "posterior_param1": 90.0,
      "posterior_param2": 9.999999999999998,
      "n_observations": 0,
      "sum_x": 0.0,
      "sum_x2": 0.0
    },
    "kelly_tracker_decay": {
      "name": "kelly_tracker_decay",
      "family": "Beta",
      "prior_mean": 0.99,
      "prior_strength": 100.0,
      "posterior_param1": 99.0,
      "posterior_param2": 1.0000000000000009,
      "n_observations": 0,
      "sum_x": 0.0,
      "sum_x2": 0.0
    },
    "regime_sticky_diagonal": {
      "name": "regime_sticky_diagonal",
      "family": "Beta",
      "prior_mean": 0.95,
      "prior_strength": 100.0,
      "posterior_param1": 95.0,
      "posterior_param2": 5.000000000000004,
      "n_observations": 0,
      "sum_x": 0.0,
      "sum_x2": 0.0
    },
    "kalman_q": {
      "name": "kalman_q",
      "family": "InverseGamma",
      "prior_mean": 1e-8,
      "prior_strength": 20.0,
      "posterior_param1": 10.0,
      "posterior_param2": 9e-8,
      "n_observations": 0,
      "sum_x": 0.0,
      "sum_x2": 0.0
    },
    "kalman_r": {
      "name": "kalman_r",
      "family": "InverseGamma",
      "prior_mean": 2.5e-9,
      "prior_strength": 20.0,
      "posterior_param1": 10.0,
      "posterior_param2": 2.25e-8,
      "n_observations": 0,
      "sum_x": 0.0,
      "sum_x2": 0.0
    },
    "momentum_normalizer_bps": {
      "name": "momentum_normalizer_bps",
      "family": "Gamma",
      "prior_mean": 20.0,
      "prior_strength": 4.0,
      "posterior_param1": 4.0,
      "posterior_param2": 0.2,
      "n_observations": 0,
      "sum_x": 0.0,
      "sum_x2": 0.0
    },
    "depth_spacing_ratio": {
      "name": "depth_spacing_ratio",
      "family": "LogNormal",
      "prior_mean": 1.5,
      "prior_strength": 5.04942884800136,
      "posterior_param1": 0.3858547515315237,
      "posterior_param2": 0.03922071315328133,
      "n_observations": 0,
      "sum_x": 0.0,
      "sum_x2": 0.0
    },
    "fill_probability_width_bps": {
      "name": "fill_probability_width_bps",
      "family": "Normal",
      "prior_mean": 2.0,
      "prior_strength": 4.0,
      "posterior_param1": 2.0,
      "posterior_param2": 0.25,
      "n_observations": 0,
      "sum_x": 0.0,
      "sum_x2": 0.0
    },
    "microprice_decay": {
      "name": "microprice_decay",
      "family": "Beta",
      "prior_mean": 0.999,
      "prior_strength": 1000.0,
      "posterior_param1": 999.0,
      "posterior_param2": 1.0000000000000009,
      "n_observations": 0,
      "sum_x": 0.0,
      "sum_x2": 0.0
    },
    "total_fills_observed": 123
  },
  "pre_fill": {
    "learned_weights": [
      0.3,
      0.25,
      0.25,
      0.1,
      0.1
    ],
    "signal_outcome_sum": [
      66.63049414661498,
      43.930901360166054,
      58.615041006329,
      55.77569232204615,
      55.76730364253239
    ],
    "signal_sq_sum": [
      62.19470389799692,
      36.60188891743861,
      53.97235977507336,
      32.91834997444721,
      32.9563960800327
    ],
    "learning_samples": 162,
    "regime_probs": [
      0.1,
      0.7,
      0.15,
      0.05
    ],
    "imbalance_ewma_mean": -1.5581936147840105,
    "imbalance_ewma_var": 1.2461519458807617,
    "flow_ewma_mean": -0.43748843777946583,
    "flow_ewma_var": 0.24648609881658218,
    "funding_ewma_mean": 0.0,
    "funding_ewma_var": 1e-12,
    "regime_trust_prev": 0.896155599657558,
    "regime_ewma_mean": 0.027670697909616723,
    "regime_ewma_var": 0.0018861434592052147,
    "changepoint_ewma_mean": 0.019888665310829008,
    "changepoint_ewma_var": 1e-12,
    "normalizer_obs_count": 13116
  },
  "enhanced": {
    "learned_weights": [
      0.12,
      0.22,
      0.18,
      0.08,
      0.08,
      0.04,
      0.08,
      0.05,
      0.08,
      0.07
    ],
    "weight_gradients": [
      0.0,
      0.0,
      0.0,
      0.0,
      0.0,
      0.0,
      0.0,
      0.0,
      0.0,
      0.0
    ],
    "learning_samples": 0,
    "prediction_sum": 0.0,
    "outcome_sum": 0.0,
    "correct_predictions": 0,
    "total_predictions": 0
  },
  "vol_filter": {
    "sigma_mean": 0.00007295180508044854,
    "sigma_std": 0.00004017248564544492,
    "regime_probs": [
      0.07647704357219201,
      0.2875076587319144,
      0.46069845487061406,
      0.17531684282527873
    ],
    "observation_count": 12198
  },
  "regime_hmm": {
    "belief": [
      0.00020441083942390227,
      0.10363998949929862,
      0.896155599657558,
      3.719560043049413e-12
    ],
    "transition_counts": [
      [
        0.0,
        0.0,
        0.0,
        0.0
      ],
      [
        0.0,
        0.0,
        0.0,
        0.0
      ],
      [
        0.0,
        0.0,
        0.0,
        0.0
      ],
      [
        0.0,
        0.0,
        0.0,
        0.0
      ]
    ],
    "observation_count": 28940,
    "recalibration_count": 35
  },
  "informed_flow": {
    "component_params": [
      {
        "mu_size": -0.40179304043383446,
        "sigma_size": 1.287984698189379,
        "lambda_0": 0.7130801640436643,
        "alpha": 0.5,
        "beta": 2.0,
        "impact_per_unit": 10.0,
        "impact_variance": 100.0
      },
      {
        "mu_size": 2.801745415238533,
        "sigma_size": 1.4825782375969387,
        "lambda_0": 5.410164065304392,
        "alpha": 0.1,
        "beta": 5.0,
        "impact_per_unit": -0.010760418380393825,
        "impact_variance": 11.374008179594735
      },
      {
        "mu_size": -0.48919771803569256,
        "sigma_size": 0.4721888593997564,
        "lambda_0": 10.0,
        "alpha": 0.8,
        "beta": 1.0,
        "impact_per_unit": -1.0485620131937976,
        "impact_variance": 11.702085847177052
      }
    ],
    "mixing_weights": [
      0.08207178149891833,
      0.7723932092406349,
      0.1455350092604468
    ],
    "observation_count": 28940
  },
  "fill_rate": {
    "lambda_0_mean": 0.03460880910642712,
    "lambda_0_variance": 0.00010236421882580924,
    "lambda_0_n_obs": 100.92459466309356,
    "delta_char_mean": 10.0,
    "delta_char_variance": 61.47500725152022,
    "delta_char_n_obs": 1.6266773193024238,
    "observation_count": 162
  },
  "kappa_own": {
    "prior_alpha": 5.0,
    "prior_beta": 0.002,
    "observation_count": 17,
    "sum_distances": 0.00017,
    "sum_sq_distances": 1.7000000000000003e-9,
    "kappa_posterior_mean": 10138.248847926267
  },
  "kappa_bid": {
    "prior_alpha": 5.0,
    "prior_beta": 0.002,
    "observation_count": 19,
    "sum_distances": 0.00019,
    "sum_sq_distances": 1.900000000000001e-9,
    "kappa_posterior_mean": 10958.90410958904
  },
  "kappa_ask": {
    "prior_alpha": 5.0,
    "prior_beta": 0.002,
    "observation_count": 12,
    "sum_distances": 0.00012000000000000002,
    "sum_sq_distances": 1.2000000000000004e-9,
    "kappa_posterior_mean": 8018.867924528302
  },
  "momentum": {
    "continuation_by_magnitude": [
      0.9044047908746202,
      0.31211610682634366,
      0.8799809935964119,
      0.7942915373569487,
      0.5,
      0.5,
      0.5,
      0.5,
      0.5,
      0.5
    ],
    "counts_by_magnitude": [
      7829,
      1019,
      194,
      20,
      0,
      0,
      0,
      0,
      0,
      0
    ],
    "prior_continuation": 0.5
  },
  "kelly_tracker": {
    "ewma_wins": 4.665067746935364,
    "n_wins": 104,
    "ewma_losses": 2.9606912601839768,
    "n_losses": 18,
    "decay": 0.99
  },
  "ensemble_weights": {
    "model_weights": [
      0.5,
      0.3,
      0.2
    ],
    "total_updates": 0
  },
  "rl_q_table": {
    "q_entries": [
      {
        "state_index": 279,
        "action_index": 1,
        "mu_n": 0.15631887974980166,
        "kappa_n": 1.01,
        "alpha": 1.5,
        "beta": 1.0001233997404395,
        "n": 1
      },
      {
        "state_index": 279,
        "action_index": 2,
        "mu_n": 0.15631887974980166,
        "kappa_n": 1.01,
        "alpha": 1.5,
        "beta": 1.0001233997404395,
        "n": 1
      },
      {
        "state_index": 279,
        "action_index": 3,
        "mu_n": 0.15631887974980166,
        "kappa_n": 1.01,
        "alpha": 1.5,
        "beta": 1.0001233997404395,
        "n": 1
      },
      {
        "state_index": 279,
        "action_index": 5,
        "mu_n": 0.15631887974980166,
        "kappa_n": 1.01,
        "alpha": 1.5,
        "beta": 1.0001233997404395,
        "n": 1
      },
      {
        "state_index": 279,
        "action_index": 8,
        "mu_n": 0.15631887974980166,
        "kappa_n": 1.01,
        "alpha": 1.5,
        "beta": 1.0001233997404395,
        "n": 1
      },
      {
        "state_index": 279,
        "action_index": 13,
        "mu_n": 0.15631887974980166,
        "kappa_n": 1.01,
        "alpha": 1.5,
        "beta": 1.0001233997404395,
        "n": 1
      },
      {
        "state_index": 279,
        "action_index": 24,
        "mu_n": 0.15709658561920367,
        "kappa_n": 2.01,
        "alpha": 2.0,
        "beta": 1.0001240136694964,
        "n": 2
      },
      {
        "state_index": 654,
        "action_index": 8,
        "mu_n": 4.2022347304255305,
        "kappa_n": 1.01,
        "alpha": 1.5,
        "beta": 1.0891768224844525,
        "n": 1
      },
      {
        "state_index": 258,
        "action_index": 2,
        "mu_n": 0.15883852895266473,
        "kappa_n": 1.01,
        "alpha": 1.5,
        "beta": 1.0001274098753132,
        "n": 1
      },
      {
        "state_index": 258,
        "action_index": 6,
        "mu_n": 6.852167335268582,
        "kappa_n": 1.01,
        "alpha": 1.5,
        "beta": 1.2371085958121348,
        "n": 1
      },
      {
        "state_index": 258,
        "action_index": 11,
        "mu_n": 6.852167335268582,
        "kappa_n": 1.01,
        "alpha": 1.5,
        "beta": 1.2371085958121348,
        "n": 1
      },
      {
        "state_index": 258,
        "action_index": 13,
        "mu_n": 6.852167335268582,
        "kappa_n": 1.01,
        "alpha": 1.5,
        "beta": 1.2371085958121348,
        "n": 1
      },
      {
        "state_index": 258,
        "action_index": 20,
        "mu_n": 6.852167335268582,
        "kappa_n": 1.01,
        "alpha": 1.5,
        "beta": 1.2371085958121348,
        "n": 1
      },
      {
        "state_index": 258,
        "action_index": 21,
        "mu_n": 6.852167335268582,
        "kappa_n": 1.01,
        "alpha": 1.5,
        "beta": 1.2371085958121348,
        "n": 1
      },
      {
        "state_index": 258,
        "action_index": 23,
        "mu_n": 6.852167335268582,
        "kappa_n": 1.01,
        "alpha": 1.5,
        "beta": 1.2371085958121348,
        "n": 1
      },
      {
        "state_index": 636,
        "action_index": 1,
        "mu_n": -0.11925219437049862,
        "kappa_n": 1.01,
        "alpha": 1.5,
        "beta": 1.000071816483604,
        "n": 1
      },
      {
        "state_index": 636,
        "action_index": 2,
        "mu_n": 1.0154373753910766,
        "kappa_n": 1.01,
        "alpha": 1.5,
        "beta": 1.0052071209698727,
        "n": 1
      },
      {
        "state_index": 636,
        "action_index": 5,
        "mu_n": 0.6265286164297951,
        "kappa_n": 1.01,
        "alpha": 1.5,
        "beta": 1.0019823174413875,
        "n": 1
      },
      {
        "state_index": 636,
        "action_index": 9,
        "mu_n": -0.11925219437049862,
        "kappa_n": 1.01,
        "alpha": 1.5,
        "beta": 1.000071816483604,
        "n": 1
      },
      {
        "state_index": 636,
        "action_index": 21,
        "mu_n": -0.11925219437049862,
        "kappa_n": 1.01,
        "alpha": 1.5,
        "beta": 1.000071816483604,
        "n": 1
      },
      {
        "state_index": 636,
        "action_index": 23,
        "mu_n": 0.6265286164297951,
        "kappa_n": 1.01,
        "alpha": 1.5,
        "beta": 1.0019823174413875,
        "n": 1
      },
      {
        "state_index": 636,
        "action_index": 24,
        "mu_n": 1.0154373753910766,
        "kappa_n": 1.01,
        "alpha": 1.5,
        "beta": 1.0052071209698727,
        "n": 1
      },
      {
        "state_index": 123,
        "action_index": 0,
        "mu_n": 2.044910359635836,
        "kappa_n": 1.01,
        "alpha": 1.5,
        "beta": 1.021117374813677,
        "n": 1
      },
      {
        "state_index": 123,
        "action_index": 1,
        "mu_n": 4.676974433551069,
        "kappa_n": 4.01,
        "alpha": 3.0,
        "beta": 3.2483526830337395,
        "n": 4
      },
      {
        "state_index": 123,
        "action_index": 2,
        "mu_n": 5.259405409319253,
        "kappa_n": 2.01,
        "alpha": 2.0,
        "beta": 2.5648041316961296,
        "n": 2
      },
      {
        "state_index": 123,
        "action_index": 3,
        "mu_n": 1.8437764354068475,
        "kappa_n": 1.01,
        "alpha": 1.5,
        "beta": 1.017167533295996,
        "n": 1
      },
      {
        "state_index": 123,
        "action_index": 4,
        "mu_n": 1.8437764354068475,
        "kappa_n": 1.01,
        "alpha": 1.5,
        "beta": 1.017167533295996,
        "n": 1
      },
      {
        "state_index": 123,
        "action_index": 5,
        "mu_n": 1.8437764354068475,
        "kappa_n": 1.01,
        "alpha": 1.5,
        "beta": 1.017167533295996,
        "n": 1
      },
      {
        "state_index": 123,
        "action_index": 6,
        "mu_n": 7.588579707077884,
        "kappa_n": 3.01,
        "alpha": 2.5,
        "beta": 4.414022945405887,
        "n": 3
      },
      {
        "state_index": 123,
        "action_index": 7,
        "mu_n": 7.889969294102374,
        "kappa_n": 3.01,
        "alpha": 2.5,
        "beta": 2.859935358083976,
        "n": 3
      },
      {
        "state_index": 123,
        "action_index": 8,
        "mu_n": 2.044910359635836,
        "kappa_n": 1.01,
        "alpha": 1.5,
        "beta": 1.021117374813677,
        "n": 1
      },
      {
        "state_index": 123,
        "action_index": 9,
        "mu_n": 4.251309966696441,
        "kappa_n": 2.01,
        "alpha": 2.0,
        "beta": 5.962582999202731,
        "n": 2
      },
      {
        "state_index": 123,
        "action_index": 10,
        "mu_n": 5.517416745429642,
        "kappa_n": 1.01,
        "alpha": 1.5,
        "beta": 1.1537315320908745,
        "n": 1
      },
      {
        "state_index": 123,
        "action_index": 11,
        "mu_n": 1.8437764354068475,
        "kappa_n": 1.01,
        "alpha": 1.5,
        "beta": 1.017167533295996,
        "n": 1
      },
      {
        "state_index": 123,
        "action_index": 12,
        "mu_n": -1.5657143230969792,
        "kappa_n": 1.01,
        "alpha": 1.5,
        "beta": 1.0123798797748327,
        "n": 1
      },
      {
        "state_index": 123,
        "action_index": 13,
        "mu_n": 2.3160213721906917,
        "kappa_n": 4.01,
        "alpha": 3.0,
        "beta": 51.059027550781195,
        "n": 4
      },
      {
        "state_index": 123,
        "action_index": 14,
        "mu_n": 1.8437764354068475,
        "kappa_n": 1.01,
        "alpha": 1.5,
        "beta": 1.017167533295996,
        "n": 1
      },
      {
        "state_index": 123,
        "action_index": 15,
        "mu_n": 6.7157144302815475,
        "kappa_n": 12.01,
        "alpha": 7.0,
        "beta": 78.00863711377585,
        "n": 12
      },
      {
        "state_index": 123,
        "action_index": 16,
        "mu_n": 1.8437764354068475,
        "kappa_n": 1.01,
        "alpha": 1.5,
        "beta": 1.017167533295996,
        "n": 1
      },
      {
        "state_index": 123,
        "action_index": 17,
        "mu_n": 2.4909071237625566,
        "kappa_n": 2.01,
        "alpha": 2.0,
        "beta": 10.45134641750948,
        "n": 2
      },
      {
        "state_index": 123,
        "action_index": 18,
        "mu_n": 3.1562008557731063,
        "kappa_n": 3.01,
        "alpha": 2.5,
        "beta": 5.401446678071065,
        "n": 3
      },
      {
        "state_index": 123,
        "action_index": 19,
        "mu_n": 1.7407940336054837,
        "kappa_n": 5.01,
        "alpha": 3.5,
        "beta": 54.382798897761475,
        "n": 5
      },
      {
        "state_index": 123,
        "action_index": 20,
        "mu_n": 7.519547548526318,
        "kappa_n": 2.01,
        "alpha": 2.0,
        "beta": 2.44486138194377,
        "n": 2
      },
      {
        "state_index": 123,
        "action_index": 21,
        "mu_n": -1.5657143230969792,
        "kappa_n": 1.01,
        "alpha": 1.5,
        "beta": 1.0123798797748327,
        "n": 1
      },
      {
        "state_index": 123,
        "action_index": 22,
        "mu_n": 1.8437764354068475,
        "kappa_n": 1.01,
        "alpha": 1.5,
        "beta": 1.017167533295996,
        "n": 1
      },
      {
        "state_index": 123,
        "action_index": 23,
        "mu_n": 6.263801413878616,
        "kappa_n": 7.01,
        "alpha": 4.5,
        "beta": 43.94345497714064,
        "n": 7
      },
      {
        "state_index": 123,
        "action_index": 24,
        "mu_n": -1.5657143230969792,
        "kappa_n": 1.01,
        "alpha": 1.5,
        "beta": 1.0123798797748327,
        "n": 1
      },
      {
        "state_index": 393,
        "action_index": 4,
        "mu_n": 4.304114090429052,
        "kappa_n": 1.01,
        "alpha": 1.5,
        "beta": 1.093553260422321,
        "n": 1
      },
      {
        "state_index": 393,
        "action_index": 13,
        "mu_n": 1.3417947481268335,
        "kappa_n": 1.01,
        "alpha": 1.5,
        "beta": 1.0090920863878088,
        "n": 1
      },
      {
        "state_index": 393,
        "action_index": 15,
        "mu_n": -0.38442174619134734,
        "kappa_n": 1.01,
        "alpha": 1.5,
        "beta": 1.0007462893986712,
        "n": 1
      },
      {
        "state_index": 393,
        "action_index": 17,
        "mu_n": 4.304114090429052,
        "kappa_n": 1.01,
        "alpha": 1.5,
        "beta": 1.093553260422321,
        "n": 1
      },
      {
        "state_index": 393,
        "action_index": 18,
        "mu_n": 4.325527593366511,
        "kappa_n": 2.01,
        "alpha": 2.0,
        "beta": 1.0940186995288999,
        "n": 2
      },
      {
        "state_index": 393,
        "action_index": 19,
        "mu_n": 4.304114090429052,
        "kappa_n": 1.01,
        "alpha": 1.5,
        "beta": 1.093553260422321,
        "n": 1
      },
      {
        "state_index": 393,
        "action_index": 22,
        "mu_n": 4.304114090429052,
        "kappa_n": 1.01,
        "alpha": 1.5,
        "beta": 1.093553260422321,
        "n": 1
      },
      {
        "state_index": 393,
        "action_index": 24,
        "mu_n": 4.304114090429052,
        "kappa_n": 1.01,
        "alpha": 1.5,
        "beta": 1.093553260422321,
        "n": 1
      },
      {
        "state_index": 600,
        "action_index": 1,
        "mu_n": 1.594125997177107,
        "kappa_n": 2.01,
        "alpha": 2.0,
        "beta": 1.0127697194167513,
        "n": 2
      },
      {
        "state_index": 600,
        "action_index": 5,
        "mu_n": 0.9546278946383739,
        "kappa_n": 1.01,
        "alpha": 1.5,
        "beta": 1.0046021378069696,
        "n": 1
      },
      {
        "state_index": 600,
        "action_index": 9,
        "mu_n": 1.5862342843197943,
        "kappa_n": 1.01,
        "alpha": 1.5,
        "beta": 1.0127065029839952,
        "n": 1
      },
      {
        "state_index": 600,
        "action_index": 19,
        "mu_n": 1.5862342843197943,
        "kappa_n": 1.01,
        "alpha": 1.5,
        "beta": 1.0127065029839952,
        "n": 1
      },
      {
        "state_index": 600,
        "action_index": 20,
        "mu_n": 5.951127027595985,
        "kappa_n": 1.01,
        "alpha": 1.5,
        "beta": 1.1788503601378462,
        "n": 1
      },
      {
        "state_index": 600,
        "action_index": 24,
        "mu_n": 4.2022347304255305,
        "kappa_n": 1.01,
        "alpha": 1.5,
        "beta": 1.0891768224844525,
        "n": 1
      },
      {
        "state_index": 411,
        "action_index": 10,
        "mu_n": 6.5031208877383735,
        "kappa_n": 2.01,
        "alpha": 2.0,
        "beta": 1.212510170934709,
        "n": 2
      },
      {
        "state_index": 411,
        "action_index": 13,
        "mu_n": 6.470927219977292,
        "kappa_n": 1.01,
        "alpha": 1.5,
        "beta": 1.2114581403855273,
        "n": 1
      },
      {
        "state_index": 411,
        "action_index": 15,
        "mu_n": 6.5031208877383735,
        "kappa_n": 2.01,
        "alpha": 2.0,
        "beta": 1.212510170934709,
        "n": 2
      },
      {
        "state_index": 411,
        "action_index": 16,
        "mu_n": 6.470927219977292,
        "kappa_n": 1.01,
        "alpha": 1.5,
        "beta": 1.2114581403855273,
        "n": 1
      },
      {
        "state_index": 417,
        "action_index": 1,
        "mu_n": 5.059088029944295,
        "kappa_n": 1.01,
        "alpha": 1.5,
        "beta": 1.1292515770583644,
        "n": 1
      },
      {
        "state_index": 417,
        "action_index": 3,
        "mu_n": 5.059088029944295,
        "kappa_n": 1.01,
        "alpha": 1.5,
        "beta": 1.1292515770583644,
        "n": 1
      },
      {
        "state_index": 417,
        "action_index": 4,
        "mu_n": 5.059088029944295,
        "kappa_n": 1.01,
        "alpha": 1.5,
        "beta": 1.1292515770583644,
        "n": 1
      },
      {
        "state_index": 417,
        "action_index": 6,
        "mu_n": 5.059088029944295,
        "kappa_n": 1.01,
        "alpha": 1.5,
        "beta": 1.1292515770583644,
        "n": 1
      },
      {
        "state_index": 417,
        "action_index": 8,
        "mu_n": 5.059088029944295,
        "kappa_n": 1.01,
        "alpha": 1.5,
        "beta": 1.1292515770583644,
        "n": 1
      },
      {
        "state_index": 417,
        "action_index": 9,
        "mu_n": 5.059088029944295,
        "kappa_n": 1.01,
        "alpha": 1.5,
        "beta": 1.1292515770583644,
        "n": 1
      },
      {
        "state_index": 417,
        "action_index": 14,
        "mu_n": 5.059088029944295,
        "kappa_n": 1.01,
        "alpha": 1.5,
        "beta": 1.1292515770583644,
        "n": 1
      },
      {
        "state_index": 417,
        "action_index": 24,
        "mu_n": 5.059088029944295,
        "kappa_n": 1.01,
        "alpha": 1.5,
        "beta": 1.1292515770583644,
        "n": 1
      },
      {
        "state_index": 177,
        "action_index": 6,
        "mu_n": 5.248822398305671,
        "kappa_n": 1.01,
        "alpha": 1.5,
        "beta": 1.1391281896732242,
        "n": 1
      },
      {
        "state_index": 177,
        "action_index": 8,
        "mu_n": 5.248822398305671,
        "kappa_n": 1.01,
        "alpha": 1.5,
        "beta": 1.1391281896732242,
        "n": 1
      },
      {
        "state_index": 177,
        "action_index": 13,
        "mu_n": 5.248822398305671,
        "kappa_n": 1.01,
        "alpha": 1.5,
        "beta": 1.1391281896732242,
        "n": 1
      },
      {
        "state_index": 366,
        "action_index": 9,
        "mu_n": 4.304114090429052,
        "kappa_n": 1.01,
        "alpha": 1.5,
        "beta": 1.093553260422321,
        "n": 1
      },
      {
        "state_index": 366,
        "action_index": 24,
        "mu_n": 1.3417947481268335,
        "kappa_n": 1.01,
        "alpha": 1.5,
        "beta": 1.0090920863878088,
        "n": 1
      },
      {
        "state_index": 414,
        "action_index": 0,
        "mu_n": 0.4193398867976514,
        "kappa_n": 2.01,
        "alpha": 2.0,
        "beta": 1.000883625851814,
        "n": 2
      },
      {
        "state_index": 414,
        "action_index": 11,
        "mu_n": 0.4193398867976514,
        "kappa_n": 2.01,
        "alpha": 2.0,
        "beta": 1.000883625851814,
        "n": 2
      },
      {
        "state_index": 414,
        "action_index": 12,
        "mu_n": 0.4172639467639996,
        "kappa_n": 1.01,
        "alpha": 1.5,
        "beta": 1.0008792514664089,
        "n": 1
      },
      {
        "state_index": 414,
        "action_index": 17,
        "mu_n": 0.4172639467639996,
        "kappa_n": 1.01,
        "alpha": 1.5,
        "beta": 1.0008792514664089,
        "n": 1
      },
      {
        "state_index": 414,
        "action_index": 19,
        "mu_n": 0.4172639467639996,
        "kappa_n": 1.01,
        "alpha": 1.5,
        "beta": 1.0008792514664089,
        "n": 1
      },
      {
        "state_index": 414,
        "action_index": 24,
        "mu_n": 0.4172639467639996,
        "kappa_n": 1.01,
        "alpha": 1.5,
        "beta": 1.0008792514664089,
        "n": 1
      },
      {
        "state_index": 231,
        "action_index": 1,
        "mu_n": 5.856371482150429,
        "kappa_n": 1.01,
        "alpha": 1.5,
        "beta": 1.1732002890315714,
        "n": 1
      },
      {
        "state_index": 231,
        "action_index": 7,
        "mu_n": 5.8855076586785415,
        "kappa_n": 2.01,
        "alpha": 2.0,
        "beta": 1.1740619820118279,
        "n": 2
      },
      {
        "state_index": 231,
        "action_index": 12,
        "mu_n": 5.856371482150429,
        "kappa_n": 1.01,
        "alpha": 1.5,
        "beta": 1.1732002890315714,
        "n": 1
      },
      {
        "state_index": 231,
        "action_index": 17,
        "mu_n": 5.8855076586785415,
        "kappa_n": 2.01,
        "alpha": 2.0,
        "beta": 1.1740619820118279,
        "n": 2
      },
      {
        "state_index": 231,
        "action_index": 21,
        "mu_n": 5.856371482150429,
        "kappa_n": 1.01,
        "alpha": 1.5,
        "beta": 1.1732002890315714,
        "n": 1
      },
      {
        "state_index": 276,
        "action_index": 14,
        "mu_n": 1.3417947481268335,
        "kappa_n": 1.01,
        "alpha": 1.5,
        "beta": 1.0090920863878088,
        "n": 1
      },
      {
        "state_index": 546,
        "action_index": 1,
        "mu_n": 5.057100277312769,
        "kappa_n": 1.01,
        "alpha": 1.5,
        "beta": 1.1291500292347243,
        "n": 1
      },
      {
        "state_index": 546,
        "action_index": 2,
        "mu_n": -6.940352419147315,
        "kappa_n": 1.01,
        "alpha": 1.5,
        "beta": 1.243250883094918,
        "n": 1
      },
      {
        "state_index": 546,
        "action_index": 9,
        "mu_n": 0.9546278946383739,
        "kappa_n": 1.01,
        "alpha": 1.5,
        "beta": 1.0046021378069696,
        "n": 1
      },
      {
        "state_index": 546,
        "action_index": 12,
        "mu_n": -6.940352419147315,
        "kappa_n": 1.01,
        "alpha": 1.5,
        "beta": 1.243250883094918,
        "n": 1
      },
      {
        "state_index": 546,
        "action_index": 21,
        "mu_n": 0.9546278946383739,
        "kappa_n": 1.01,
        "alpha": 1.5,
        "beta": 1.0046021378069696,
        "n": 1
      },
      {
        "state_index": 546,
        "action_index": 22,
        "mu_n": -3.0077521242557363,
        "kappa_n": 2.01,
        "alpha": 2.0,
        "beta": 16.94134940592093,
        "n": 2
      },
      {
        "state_index": 546,
        "action_index": 24,
        "mu_n": -6.940352419147315,
        "kappa_n": 1.01,
        "alpha": 1.5,
        "beta": 1.243250883094918,
        "n": 1
      },
      {
        "state_index": 15,
        "action_index": 0,
        "mu_n": 1.7507390127756608,
        "kappa_n": 1.01,
        "alpha": 1.5,
        "beta": 1.0154786898088162,
        "n": 1
      },
      {
        "state_index": 15,
        "action_index": 1,
        "mu_n": 1.4023437745148482,
        "kappa_n": 2.01,
        "alpha": 2.0,
        "beta": 1.0098820045111507,
        "n": 2
      },
      {
        "state_index": 15,
        "action_index": 2,
        "mu_n": 2.716035758385946,
        "kappa_n": 6.01,
        "alpha": 4.0,
        "beta": 34.52730642000135,
        "n": 6
      },
      {
        "state_index": 15,
        "action_index": 3,
        "mu_n": -0.16034815650000442,
        "kappa_n": 3.01,
        "alpha": 2.5,
        "beta": 21.770262138495035,
        "n": 3
      },
      {
        "state_index": 15,
        "action_index": 4,
        "mu_n": 1.7594491571178286,
        "kappa_n": 2.01,
        "alpha": 2.0,
        "beta": 1.0155556982158251,
        "n": 2
      },
      {
        "state_index": 15,
        "action_index": 5,
        "mu_n": -0.3278699487291934,
        "kappa_n": 1.01,
        "alpha": 1.5,
        "beta": 1.0005428684515625,
        "n": 1
      },
      {
        "state_index": 15,
        "action_index": 6,
        "mu_n": 1.605318926391962,
        "kappa_n": 2.01,
        "alpha": 2.0,
        "beta": 1.012949670498547,
        "n": 2
      },
      {
        "state_index": 15,
        "action_index": 7,
        "mu_n": 1.7507390127756608,
        "kappa_n": 1.01,
        "alpha": 1.5,
        "beta": 1.0154786898088162,
        "n": 1
      },
      {
        "state_index": 15,
        "action_index": 8,
        "mu_n": 1.4023437745148482,
        "kappa_n": 2.01,
        "alpha": 2.0,
        "beta": 1.0098820045111507,
        "n": 2
      },
      {
        "state_index": 15,
        "action_index": 9,
        "mu_n": -1.1356203842363621,
        "kappa_n": 3.01,
        "alpha": 2.5,
        "beta": 25.095723224113296,
        "n": 3
      },
      {
        "state_index": 15,
        "action_index": 10,
        "mu_n": -0.3278699487291934,
        "kappa_n": 1.01,
        "alpha": 1.5,
        "beta": 1.0005428684515625,
        "n": 1
      },
      {
        "state_index": 15,
        "action_index": 11,
        "mu_n": 2.8929588633935666,
        "kappa_n": 5.01,
        "alpha": 3.5,
        "beta": 1.4669362432930941,
        "n": 5
      },
      {
        "state_index": 15,
        "action_index": 12,
        "mu_n": 1.3954014786014082,
        "kappa_n": 1.01,
        "alpha": 1.5,
        "beta": 1.009833083696739,
        "n": 1
      },
      {
        "state_index": 15,
        "action_index": 13,
        "mu_n": 1.3954014786014082,
        "kappa_n": 1.01,
        "alpha": 1.5,
        "beta": 1.009833083696739,
        "n": 1
      },
      {
        "state_index": 15,
        "action_index": 14,
        "mu_n": 4.146969628058875,
        "kappa_n": 6.01,
        "alpha": 4.0,
        "beta": 14.387210595720031,
        "n": 6
      },
      {
        "state_index": 15,
        "action_index": 15,
        "mu_n": -0.3278699487291934,
        "kappa_n": 1.01,
        "alpha": 1.5,
        "beta": 1.0005428684515625,
        "n": 1
      },
      {
        "state_index": 15,
        "action_index": 16,
        "mu_n": 0.3144443278354314,
        "kappa_n": 4.01,
        "alpha": 3.0,
        "beta": 37.77983445979513,
        "n": 4
      },
      {
        "state_index": 15,
        "action_index": 17,
        "mu_n": -0.3278699487291934,
        "kappa_n": 1.01,
        "alpha": 1.5,
        "beta": 1.0005428684515625,
        "n": 1
      },
      {
        "state_index": 15,
        "action_index": 18,
        "mu_n": -0.3295011425039655,
        "kappa_n": 2.01,
        "alpha": 2.0,
        "beta": 1.00054556928963,
        "n": 2
      },
      {
        "state_index": 15,
        "action_index": 19,
        "mu_n": 1.109922087263953,
        "kappa_n": 2.01,
        "alpha": 2.0,
        "beta": 3.098900858595298,
        "n": 2
      },
      {
        "state_index": 15,
        "action_index": 20,
        "mu_n": 1.644956810050476,
        "kappa_n": 4.01,
        "alpha": 3.0,
        "beta": 23.13857039562377,
        "n": 4
      },
      {
        "state_index": 15,
        "action_index": 21,
        "mu_n": 3.579497405976325,
        "kappa_n": 11.01,
        "alpha": 6.5,
        "beta": 29.012143245541573,
        "n": 11
      },
      {
        "state_index": 15,
        "action_index": 22,
        "mu_n": 2.4247714152553868,
        "kappa_n": 6.01,
        "alpha": 4.0,
        "beta": 43.486555324788334,
        "n": 6
      },
      {
        "state_index": 15,
        "action_index": 23,
        "mu_n": 1.7594491571178286,
        "kappa_n": 2.01,
        "alpha": 2.0,
        "beta": 1.0155556982158251,
        "n": 2
      },
      {
        "state_index": 15,
        "action_index": 24,
        "mu_n": -0.28326540239657155,
        "kappa_n": 2.01,
        "alpha": 2.0,
        "beta": 14.604739196346138,
        "n": 2
      },
      {
        "state_index": 150,
        "action_index": 1,
        "mu_n": 5.248822398305671,
        "kappa_n": 1.01,
        "alpha": 1.5,
        "beta": 1.1391281896732242,
        "n": 1
      },
      {
        "state_index": 150,
        "action_index": 11,
        "mu_n": 5.248822398305671,
        "kappa_n": 1.01,
        "alpha": 1.5,
        "beta": 1.1391281896732242,
        "n": 1
      },
      {
        "state_index": 150,
        "action_index": 15,
        "mu_n": 5.248822398305671,
        "kappa_n": 1.01,
        "alpha": 1.5,
        "beta": 1.1391281896732242,
        "n": 1
      },
      {
        "state_index": 150,
        "action_index": 21,
        "mu_n": 5.248822398305671,
        "kappa_n": 1.01,
        "alpha": 1.5,
        "beta": 1.1391281896732242,
        "n": 1
      },
      {
        "state_index": 150,
        "action_index": 24,
        "mu_n": 5.248822398305671,
        "kappa_n": 1.01,
        "alpha": 1.5,
        "beta": 1.1391281896732242,
        "n": 1
      },
      {
        "state_index": 519,
        "action_index": 1,
        "mu_n": 7.810830552558838,
        "kappa_n": 1.01,
        "alpha": 1.5,
        "beta": 1.3080958232999724,
        "n": 1
      },
      {
        "state_index": 519,
        "action_index": 21,
        "mu_n": 7.810830552558838,
        "kappa_n": 1.01,
        "alpha": 1.5,
        "beta": 1.3080958232999724,
        "n": 1
      },
      {
        "state_index": 501,
        "action_index": 7,
        "mu_n": -1.2591491395042056,
        "kappa_n": 1.01,
        "alpha": 1.5,
        "beta": 1.0080065556053466,
        "n": 1
      },
      {
        "state_index": 501,
        "action_index": 11,
        "mu_n": -1.2591491395042056,
        "kappa_n": 1.01,
        "alpha": 1.5,
        "beta": 1.0080065556053466,
        "n": 1
      },
      {
        "state_index": 501,
        "action_index": 15,
        "mu_n": -1.2591491395042056,
        "kappa_n": 1.01,
        "alpha": 1.5,
        "beta": 1.0080065556053466,
        "n": 1
      },
      {
        "state_index": 501,
        "action_index": 19,
        "mu_n": -1.2591491395042056,
        "kappa_n": 1.01,
        "alpha": 1.5,
        "beta": 1.0080065556053466,
        "n": 1
      },
      {
        "state_index": 501,
        "action_index": 23,
        "mu_n": -1.2591491395042056,
        "kappa_n": 1.01,
        "alpha": 1.5,
        "beta": 1.0080065556053466,
        "n": 1
      },
      {
        "state_index": 204,
        "action_index": 6,
        "mu_n": 5.856371482150429,
        "kappa_n": 1.01,
        "alpha": 1.5,
        "beta": 1.1732002890315714,
        "n": 1
      },
      {
        "state_index": 627,
        "action_index": 1,
        "mu_n": 4.2022347304255305,
        "kappa_n": 1.01,
        "alpha": 1.5,
        "beta": 1.0891768224844525,
        "n": 1
      },
      {
        "state_index": 627,
        "action_index": 5,
        "mu_n": 5.951127027595985,
        "kappa_n": 1.01,
        "alpha": 1.5,
        "beta": 1.1788503601378462,
        "n": 1
      },
      {
        "state_index": 627,
        "action_index": 19,
        "mu_n": 4.2022347304255305,
        "kappa_n": 1.01,
        "alpha": 1.5,
        "beta": 1.0891768224844525,
        "n": 1
      },
      {
        "state_index": 222,
        "action_index": 24,
        "mu_n": 6.852167335268582,
        "kappa_n": 1.01,
        "alpha": 1.5,
        "beta": 1.2371085958121348,
        "n": 1
      },
      {
        "state_index": 96,
        "action_index": 0,
        "mu_n": 0.589019529253216,
        "kappa_n": 2.01,
        "alpha": 2.0,
        "beta": 35.66803754205431,
        "n": 2
      },
      {
        "state_index": 96,
        "action_index": 1,
        "mu_n": 3.110259247211722,
        "kappa_n": 2.01,
        "alpha": 2.0,
        "beta": 1.4414667644189845,
        "n": 2
      },
      {
        "state_index": 96,
        "action_index": 2,
        "mu_n": 0.6532627382510726,
        "kappa_n": 1.01,
        "alpha": 1.5,
        "beta": 1.0021550986361958,
        "n": 1
      },
      {
        "state_index": 96,
        "action_index": 3,
        "mu_n": 0.6532627382510726,
        "kappa_n": 1.01,
        "alpha": 1.5,
        "beta": 1.0021550986361958,
        "n": 1
      },
      {
        "state_index": 96,
        "action_index": 4,
        "mu_n": 0.6532627382510726,
        "kappa_n": 1.01,
        "alpha": 1.5,
        "beta": 1.0021550986361958,
        "n": 1
      },
      {
        "state_index": 96,
        "action_index": 5,
        "mu_n": 3.715438701404503,
        "kappa_n": 1.01,
        "alpha": 1.5,
        "beta": 1.0697126479566665,
        "n": 1
      },
      {
        "state_index": 96,
        "action_index": 6,
        "mu_n": 2.97638930326251,
        "kappa_n": 1.01,
        "alpha": 1.5,
        "beta": 1.0447374110871062,
        "n": 1
      },
      {
        "state_index": 96,
        "action_index": 7,
        "mu_n": 4.050960387587616,
        "kappa_n": 3.01,
        "alpha": 2.5,
        "beta": 4.442387566133412,
        "n": 3
      },
      {
        "state_index": 96,
        "action_index": 8,
        "mu_n": 2.9911972102439157,
        "kappa_n": 2.01,
        "alpha": 2.0,
        "beta": 1.0449599852716192,
        "n": 2
      },
      {
        "state_index": 96,
        "action_index": 9,
        "mu_n": 2.97638930326251,
        "kappa_n": 1.01,
        "alpha": 1.5,
        "beta": 1.0447374110871062,
        "n": 1
      },
      {
        "state_index": 96,
        "action_index": 10,
        "mu_n": -5.24341021388979,
        "kappa_n": 1.01,
        "alpha": 1.5,
        "beta": 1.138841420889175,
        "n": 1
      },
      {
        "state_index": 96,
        "action_index": 11,
        "mu_n": -5.24341021388979,
        "kappa_n": 1.01,
        "alpha": 1.5,
        "beta": 1.138841420889175,
        "n": 1
      },
      {
        "state_index": 96,
        "action_index": 12,
        "mu_n": 5.517416745429642,
        "kappa_n": 1.01,
        "alpha": 1.5,
        "beta": 1.1537315320908745,
        "n": 1
      },
      {
        "state_index": 96,
        "action_index": 13,
        "mu_n": 3.715438701404503,
        "kappa_n": 1.01,
        "alpha": 1.5,
        "beta": 1.0697126479566665,
        "n": 1
      },
      {
        "state_index": 96,
        "action_index": 14,
        "mu_n": 6.119885518859856,
        "kappa_n": 1.01,
        "alpha": 1.5,
        "beta": 1.1891376437579504,
        "n": 1
      },
      {
        "state_index": 96,
        "action_index": 15,
        "mu_n": -6.65266292546218,
        "kappa_n": 1.01,
        "alpha": 1.5,
        "beta": 1.223502516199086,
        "n": 1
      },
      {
        "state_index": 96,
        "action_index": 16,
        "mu_n": 0.6565128016254561,
        "kappa_n": 2.01,
        "alpha": 2.0,
        "beta": 1.002165820519958,
        "n": 2
      },
      {
        "state_index": 96,
        "action_index": 17,
        "mu_n": 2.044910359635836,
        "kappa_n": 1.01,
        "alpha": 1.5,
        "beta": 1.021117374813677,
        "n": 1
      },
      {
        "state_index": 96,
        "action_index": 18,
        "mu_n": 0.6532627382510726,
        "kappa_n": 1.01,
        "alpha": 1.5,
        "beta": 1.0021550986361958,
        "n": 1
      },
      {
        "state_index": 96,
        "action_index": 19,
        "mu_n": 4.051120101885193,
        "kappa_n": 1.01,
        "alpha": 1.5,
        "beta": 1.0828784491034864,
        "n": 1
      },
      {
        "state_index": 96,
        "action_index": 20,
        "mu_n": 6.1605492100150725,
        "kappa_n": 3.01,
        "alpha": 2.5,
        "beta": 1.1903943722879036,
        "n": 3
      },
      {
        "state_index": 96,
        "action_index": 21,
        "mu_n": 2.4742851470069427,
        "kappa_n": 1.01,
        "alpha": 1.5,
        "beta": 1.0309165392929307,
        "n": 1
      },
      {
        "state_index": 96,
        "action_index": 22,
        "mu_n": 0.6532627382510726,
        "kappa_n": 1.01,
        "alpha": 1.5,
        "beta": 1.0021550986361958,
        "n": 1
      },
      {
        "state_index": 96,
        "action_index": 23,
        "mu_n": 5.517416745429642,
        "kappa_n": 1.01,
        "alpha": 1.5,
        "beta": 1.1537315320908745,
        "n": 1
      },
      {
        "state_index": 96,
        "action_index": 24,
        "mu_n": 2.97638930326251,
        "kappa_n": 1.01,
        "alpha": 1.5,
        "beta": 1.0447374110871062,
        "n": 1
      },
      {
        "state_index": 303,
        "action_index": 8,
        "mu_n": 1.3417947481268335,
        "kappa_n": 1.01,
        "alpha": 1.5,
        "beta": 1.0090920863878088,
        "n": 1
      },
      {
        "state_index": 303,
        "action_index": 18,
        "mu_n": 1.3417947481268335,
        "kappa_n": 1.01,
        "alpha": 1.5,
        "beta": 1.0090920863878088,
        "n": 1
      },
      {
        "state_index": 69,
        "action_index": 0,
        "mu_n": 1.5973718029939818,
        "kappa_n": 1.01,
        "alpha": 1.5,
        "beta": 1.0128855632188511,
        "n": 1
      },
      {
        "state_index": 69,
        "action_index": 1,
        "mu_n": 5.2293194736304605,
        "kappa_n": 1.01,
        "alpha": 1.5,
        "beta": 1.1380961998943184,
        "n": 1
      },
      {
        "state_index": 69,
        "action_index": 2,
        "mu_n": 2.7340417937298627,
        "kappa_n": 2.01,
        "alpha": 2.0,
        "beta": 1.0375617972625546,
        "n": 2
      },
      {
        "state_index": 69,
        "action_index": 3,
        "mu_n": -6.65266292546218,
        "kappa_n": 1.01,
        "alpha": 1.5,
        "beta": 1.223502516199086,
        "n": 1
      },
      {
        "state_index": 69,
        "action_index": 4,
        "mu_n": 2.4742851470069427,
        "kappa_n": 1.01,
        "alpha": 1.5,
        "beta": 1.0309165392929307,
        "n": 1
      },
      {
        "state_index": 69,
        "action_index": 5,
        "mu_n": 2.044910359635836,
        "kappa_n": 1.01,
        "alpha": 1.5,
        "beta": 1.021117374813677,
        "n": 1
      },
      {
        "state_index": 69,
        "action_index": 6,
        "mu_n": 6.415617395868963,
        "kappa_n": 1.01,
        "alpha": 1.5,
        "beta": 1.207858740179391,
        "n": 1
      },
      {
        "state_index": 69,
        "action_index": 7,
        "mu_n": -6.65266292546218,
        "kappa_n": 1.01,
        "alpha": 1.5,
        "beta": 1.223502516199086,
        "n": 1
      },
      {
        "state_index": 69,
        "action_index": 8,
        "mu_n": -6.65266292546218,
        "kappa_n": 1.01,
        "alpha": 1.5,
        "beta": 1.223502516199086,
        "n": 1
      },
      {
        "state_index": 69,
        "action_index": 9,
        "mu_n": -6.65266292546218,
        "kappa_n": 1.01,
        "alpha": 1.5,
        "beta": 1.223502516199086,
        "n": 1
      },
      {
        "state_index": 69,
        "action_index": 10,
        "mu_n": 3.6525434684316154,
        "kappa_n": 3.01,
        "alpha": 2.5,
        "beta": 5.932401448503523,
        "n": 3
      },
      {
        "state_index": 69,
        "action_index": 11,
        "mu_n": 2.4865950233602114,
        "kappa_n": 2.01,
        "alpha": 2.0,
        "beta": 1.0310703529212537,
        "n": 2
      },
      {
        "state_index": 69,
        "action_index": 12,
        "mu_n": 4.483126075082615,
        "kappa_n": 1.01,
        "alpha": 1.5,
        "beta": 1.1014970179956827,
        "n": 1
      },
      {
        "state_index": 69,
        "action_index": 13,
        "mu_n": 4.483126075082615,
        "kappa_n": 1.01,
        "alpha": 1.5,
        "beta": 1.1014970179956827,
        "n": 1
      },
      {
        "state_index": 69,
        "action_index": 14,
        "mu_n": 3.715438701404503,
        "kappa_n": 1.01,
        "alpha": 1.5,
        "beta": 1.0697126479566665,
        "n": 1
      },
      {
        "state_index": 69,
        "action_index": 15,
        "mu_n": 2.044910359635836,
        "kappa_n": 1.01,
        "alpha": 1.5,
        "beta": 1.021117374813677,
        "n": 1
      },
      {
        "state_index": 69,
        "action_index": 16,
        "mu_n": 3.715438701404503,
        "kappa_n": 1.01,
        "alpha": 1.5,
        "beta": 1.0697126479566665,
        "n": 1
      },
      {
        "state_index": 69,
        "action_index": 17,
        "mu_n": -6.685760750961993,
        "kappa_n": 2.01,
        "alpha": 2.0,
        "beta": 1.2246144690159968,
        "n": 2
      },
      {
        "state_index": 69,
        "action_index": 18,
        "mu_n": 4.051120101885193,
        "kappa_n": 1.01,
        "alpha": 1.5,
        "beta": 1.0828784491034864,
        "n": 1
      },
      {
        "state_index": 69,
        "action_index": 19,
        "mu_n": -2.3460746579198037,
        "kappa_n": 4.01,
        "alpha": 3.0,
        "beta": 53.02703035496884,
        "n": 4
      },
      {
        "state_index": 69,
        "action_index": 20,
        "mu_n": 3.715438701404503,
        "kappa_n": 1.01,
        "alpha": 1.5,
        "beta": 1.0697126479566665,
        "n": 1
      },
      {
        "state_index": 69,
        "action_index": 21,
        "mu_n": 0.6532627382510726,
        "kappa_n": 1.01,
        "alpha": 1.5,
        "beta": 1.0021550986361958,
        "n": 1
      },
      {
        "state_index": 69,
        "action_index": 22,
        "mu_n": 5.517416745429642,
        "kappa_n": 1.01,
        "alpha": 1.5,
        "beta": 1.1537315320908745,
        "n": 1
      },
      {
        "state_index": 69,
        "action_index": 23,
        "mu_n": -6.65266292546218,
        "kappa_n": 1.01,
        "alpha": 1.5,
        "beta": 1.223502516199086,
        "n": 1
      },
      {
        "state_index": 69,
        "action_index": 24,
        "mu_n": 4.139454186856941,
        "kappa_n": 2.01,
        "alpha": 2.0,
        "beta": 3.0810889961521664,
        "n": 2
      },
      {
        "state_index": 663,
        "action_index": 0,
        "mu_n": -3.5210035566932234,
        "kappa_n": 1.01,
        "alpha": 1.5,
        "beta": 1.0626072035335439,
        "n": 1
      },
      {
        "state_index": 663,
        "action_index": 2,
        "mu_n": -0.11925219437049862,
        "kappa_n": 1.01,
        "alpha": 1.5,
        "beta": 1.000071816483604,
        "n": 1
      },
      {
        "state_index": 663,
        "action_index": 3,
        "mu_n": -3.5210035566932234,
        "kappa_n": 1.01,
        "alpha": 1.5,
        "beta": 1.0626072035335439,
        "n": 1
      },
      {
        "state_index": 663,
        "action_index": 7,
        "mu_n": 0.6265286164297951,
        "kappa_n": 1.01,
        "alpha": 1.5,
        "beta": 1.0019823174413875,
        "n": 1
      },
      {
        "state_index": 663,
        "action_index": 9,
        "mu_n": 0.6265286164297951,
        "kappa_n": 1.01,
        "alpha": 1.5,
        "beta": 1.0019823174413875,
        "n": 1
      },
      {
        "state_index": 663,
        "action_index": 11,
        "mu_n": -0.11925219437049862,
        "kappa_n": 1.01,
        "alpha": 1.5,
        "beta": 1.000071816483604,
        "n": 1
      },
      {
        "state_index": 663,
        "action_index": 12,
        "mu_n": 0.6265286164297951,
        "kappa_n": 1.01,
        "alpha": 1.5,
        "beta": 1.0019823174413875,
        "n": 1
      },
      {
        "state_index": 663,
        "action_index": 13,
        "mu_n": -0.11925219437049862,
        "kappa_n": 1.01,
        "alpha": 1.5,
        "beta": 1.000071816483604,
        "n": 1
      },
      {
        "state_index": 663,
        "action_index": 14,
        "mu_n": 0.6265286164297951,
        "kappa_n": 1.01,
        "alpha": 1.5,
        "beta": 1.0019823174413875,
        "n": 1
      },
      {
        "state_index": 663,
        "action_index": 15,
        "mu_n": 0.6265286164297951,
        "kappa_n": 1.01,
        "alpha": 1.5,
        "beta": 1.0019823174413875,
        "n": 1
      },
      {
        "state_index": 663,
        "action_index": 18,
        "mu_n": 0.6265286164297951,
        "kappa_n": 1.01,
        "alpha": 1.5,
        "beta": 1.0019823174413875,
        "n": 1
      },
      {
        "state_index": 663,
        "action_index": 19,
        "mu_n": -0.11925219437049862,
        "kappa_n": 1.01,
        "alpha": 1.5,
        "beta": 1.000071816483604,
        "n": 1
      },
      {
        "state_index": 663,
        "action_index": 23,
        "mu_n": -0.11925219437049862,
        "kappa_n": 1.01,
        "alpha": 1.5,
        "beta": 1.000071816483604,
        "n": 1
      },
      {
        "state_index": 87,
        "action_index": 11,
        "mu_n": 2.4742851470069427,
        "kappa_n": 1.01,
        "alpha": 1.5,
        "beta": 1.0309165392929307,
        "n": 1
      },
      {
        "state_index": 87,
        "action_index": 13,
        "mu_n": 1.293784194817734,
        "kappa_n": 1.01,
        "alpha": 1.5,
        "beta": 1.008453081590939,
        "n": 1
      },
      {
        "state_index": 87,
        "action_index": 15,
        "mu_n": 1.293784194817734,
        "kappa_n": 1.01,
        "alpha": 1.5,
        "beta": 1.008453081590939,
        "n": 1
      },
      {
        "state_index": 114,
        "action_index": 5,
        "mu_n": 2.97638930326251,
        "kappa_n": 1.01,
        "alpha": 1.5,
        "beta": 1.0447374110871062,
        "n": 1
      },
      {
        "state_index": 114,
        "action_index": 11,
        "mu_n": 1.3002209321053846,
        "kappa_n": 2.01,
        "alpha": 2.0,
        "beta": 1.0084951367232322,
        "n": 2
      },
      {
        "state_index": 114,
        "action_index": 18,
        "mu_n": 1.293784194817734,
        "kappa_n": 1.01,
        "alpha": 1.5,
        "beta": 1.008453081590939,
        "n": 1
      },
      {
        "state_index": 114,
        "action_index": 21,
        "mu_n": 1.293784194817734,
        "kappa_n": 1.01,
        "alpha": 1.5,
        "beta": 1.008453081590939,
        "n": 1
      },
      {
        "state_index": 42,
        "action_index": 0,
        "mu_n": 6.780779761984103,
        "kappa_n": 1.01,
        "alpha": 1.5,
        "beta": 1.2321938196116926,
        "n": 1
      },
      {
        "state_index": 42,
        "action_index": 1,
        "mu_n": 1.395517304542909,
        "kappa_n": 1.01,
        "alpha": 1.5,
        "beta": 1.0098347161637575,
        "n": 1
      },
      {
        "state_index": 42,
        "action_index": 6,
        "mu_n": 1.3954014786014082,
        "kappa_n": 1.01,
        "alpha": 1.5,
        "beta": 1.009833083696739,
        "n": 1
      },
      {
        "state_index": 42,
        "action_index": 7,
        "mu_n": 1.5973718029939818,
        "kappa_n": 1.01,
        "alpha": 1.5,
        "beta": 1.0128855632188511,
        "n": 1
      },
      {
        "state_index": 42,
        "action_index": 9,
        "mu_n": -5.24341021388979,
        "kappa_n": 1.01,
        "alpha": 1.5,
        "beta": 1.138841420889175,
        "n": 1
      },
      {
        "state_index": 42,
        "action_index": 10,
        "mu_n": 1.5973718029939818,
        "kappa_n": 1.01,
        "alpha": 1.5,
        "beta": 1.0128855632188511,
        "n": 1
      },
      {
        "state_index": 42,
        "action_index": 11,
        "mu_n": 1.5973718029939818,
        "kappa_n": 1.01,
        "alpha": 1.5,
        "beta": 1.0128855632188511,
        "n": 1
      },
      {
        "state_index": 42,
        "action_index": 12,
        "mu_n": 3.715438701404503,
        "kappa_n": 1.01,
        "alpha": 1.5,
        "beta": 1.0697126479566665,
        "n": 1
      },
      {
        "state_index": 42,
        "action_index": 13,
        "mu_n": 6.119885518859856,
        "kappa_n": 1.01,
        "alpha": 1.5,
        "beta": 1.1891376437579504,
        "n": 1
      },
      {
        "state_index": 42,
        "action_index": 14,
        "mu_n": 2.720506933364863,
        "kappa_n": 1.01,
        "alpha": 1.5,
        "beta": 1.0373758477711559,
        "n": 1
      },
      {
        "state_index": 42,
        "action_index": 16,
        "mu_n": 2.4742851470069427,
        "kappa_n": 1.01,
        "alpha": 1.5,
        "beta": 1.0309165392929307,
        "n": 1
      },
      {
        "state_index": 42,
        "action_index": 17,
        "mu_n": -0.3278699487291934,
        "kappa_n": 1.01,
        "alpha": 1.5,
        "beta": 1.0005428684515625,
        "n": 1
      },
      {
        "state_index": 42,
        "action_index": 18,
        "mu_n": 4.557968538121273,
        "kappa_n": 1.01,
        "alpha": 1.5,
        "beta": 1.104914139832242,
        "n": 1
      },
      {
        "state_index": 42,
        "action_index": 19,
        "mu_n": 3.715438701404503,
        "kappa_n": 1.01,
        "alpha": 1.5,
        "beta": 1.0697126479566665,
        "n": 1
      },
      {
        "state_index": 42,
        "action_index": 20,
        "mu_n": 1.5973718029939818,
        "kappa_n": 1.01,
        "alpha": 1.5,
        "beta": 1.0128855632188511,
        "n": 1
      },
      {
        "state_index": 42,
        "action_index": 21,
        "mu_n": 1.395517304542909,
        "kappa_n": 1.01,
        "alpha": 1.5,
        "beta": 1.0098347161637575,
        "n": 1
      },
      {
        "state_index": 42,
        "action_index": 22,
        "mu_n": 1.5973718029939818,
        "kappa_n": 1.01,
        "alpha": 1.5,
        "beta": 1.0128855632188511,
        "n": 1
      },
      {
        "state_index": 42,
        "action_index": 23,
        "mu_n": 6.119885518859856,
        "kappa_n": 1.01,
        "alpha": 1.5,
        "beta": 1.1891376437579504,
        "n": 1
      },
      {
        "state_index": 312,
        "action_index": 0,
        "mu_n": 1.571695938279263,
        "kappa_n": 1.01,
        "alpha": 1.5,
        "beta": 1.0124746520181378,
        "n": 1
      },
      {
        "state_index": 312,
        "action_index": 8,
        "mu_n": 1.571695938279263,
        "kappa_n": 1.01,
        "alpha": 1.5,
        "beta": 1.0124746520181378,
        "n": 1
      },
      {
        "state_index": 312,
        "action_index": 16,
        "mu_n": 4.902242225122783,
        "kappa_n": 1.01,
        "alpha": 1.5,
        "beta": 1.1213614931105726,
        "n": 1
      },
      {
        "state_index": 312,
        "action_index": 20,
        "mu_n": 1.571695938279263,
        "kappa_n": 1.01,
        "alpha": 1.5,
        "beta": 1.0124746520181378,
        "n": 1
      },
      {
        "state_index": 312,
        "action_index": 21,
        "mu_n": 1.571695938279263,
        "kappa_n": 1.01,
        "alpha": 1.5,
        "beta": 1.0124746520181378,
        "n": 1
      },
      {
        "state_index": 312,
        "action_index": 22,
        "mu_n": 4.902242225122783,
        "kappa_n": 1.01,
        "alpha": 1.5,
        "beta": 1.1213614931105726,
        "n": 1
      },
      {
        "state_index": 312,
        "action_index": 23,
        "mu_n": 1.571695938279263,
        "kappa_n": 1.01,
        "alpha": 1.5,
        "beta": 1.0124746520181378,
        "n": 1
      },
      {
        "state_index": 609,
        "action_index": 4,
        "mu_n": 3.4428657779544842,
        "kappa_n": 1.01,
        "alpha": 1.5,
        "beta": 1.0598592900633013,
        "n": 1
      },
      {
        "state_index": 609,
        "action_index": 14,
        "mu_n": 5.110534678204357,
        "kappa_n": 1.01,
        "alpha": 1.5,
        "beta": 1.131893701720503,
        "n": 1
      },
      {
        "state_index": 609,
        "action_index": 15,
        "mu_n": 1.0154373753910766,
        "kappa_n": 1.01,
        "alpha": 1.5,
        "beta": 1.0052071209698727,
        "n": 1
      },
      {
        "state_index": 609,
        "action_index": 16,
        "mu_n": 1.0204893026318282,
        "kappa_n": 2.01,
        "alpha": 2.0,
        "beta": 1.0052330270443497,
        "n": 2
      },
      {
        "state_index": 609,
        "action_index": 20,
        "mu_n": 5.110534678204357,
        "kappa_n": 1.01,
        "alpha": 1.5,
        "beta": 1.131893701720503,
        "n": 1
      },
      {
        "state_index": 609,
        "action_index": 23,
        "mu_n": 5.110534678204357,
        "kappa_n": 1.01,
        "alpha": 1.5,
        "beta": 1.131893701720503,
        "n": 1
      },
      {
        "state_index": 609,
        "action_index": 24,
        "mu_n": 1.0154373753910766,
        "kappa_n": 1.01,
        "alpha": 1.5,
        "beta": 1.0052071209698727,
        "n": 1
      },
      {
        "state_index": 285,
        "action_index": 10,
        "mu_n": 1.571695938279263,
        "kappa_n": 1.01,
        "alpha": 1.5,
        "beta": 1.0124746520181378,
        "n": 1
      },
      {
        "state_index": 285,
        "action_index": 14,
        "mu_n": 4.902242225122783,
        "kappa_n": 1.01,
        "alpha": 1.5,
        "beta": 1.1213614931105726,
        "n": 1
      },
      {
        "state_index": 285,
        "action_index": 20,
        "mu_n": 4.902242225122783,
        "kappa_n": 1.01,
        "alpha": 1.5,
        "beta": 1.1213614931105726,
        "n": 1
      },
      {
        "state_index": 285,
        "action_index": 23,
        "mu_n": 1.571695938279263,
        "kappa_n": 1.01,
        "alpha": 1.5,
        "beta": 1.0124746520181378,
        "n": 1
      },
      {
        "state_index": 573,
        "action_index": 0,
        "mu_n": 5.951127027595985,
        "kappa_n": 1.01,
        "alpha": 1.5,
        "beta": 1.1788503601378462,
        "n": 1
      },
      {
        "state_index": 573,
        "action_index": 4,
        "mu_n": 0.9546278946383739,
        "kappa_n": 1.01,
        "alpha": 1.5,
        "beta": 1.0046021378069696,
        "n": 1
      },
      {
        "state_index": 573,
        "action_index": 5,
        "mu_n": 1.5862342843197943,
        "kappa_n": 1.01,
        "alpha": 1.5,
        "beta": 1.0127065029839952,
        "n": 1
      },
      {
        "state_index": 573,
        "action_index": 16,
        "mu_n": 1.5862342843197943,
        "kappa_n": 1.01,
        "alpha": 1.5,
        "beta": 1.0127065029839952,
        "n": 1
      },
      {
        "state_index": 573,
        "action_index": 17,
        "mu_n": 1.5862342843197943,
        "kappa_n": 1.01,
        "alpha": 1.5,
        "beta": 1.0127065029839952,
        "n": 1
      },
      {
        "state_index": 573,
        "action_index": 23,
        "mu_n": 5.951127027595985,
        "kappa_n": 1.01,
        "alpha": 1.5,
        "beta": 1.1788503601378462,
        "n": 1
      },
      {
        "state_index": 573,
        "action_index": 24,
        "mu_n": 1.5862342843197943,
        "kappa_n": 1.01,
        "alpha": 1.5,
        "beta": 1.0127065029839952,
        "n": 1
      },
      {
        "state_index": 474,
        "action_index": 16,
        "mu_n": -1.2591491395042056,
        "kappa_n": 1.01,
        "alpha": 1.5,
        "beta": 1.0080065556053466,
        "n": 1
      },
      {
        "state_index": 474,
        "action_index": 22,
        "mu_n": -1.2591491395042056,
        "kappa_n": 1.01,
        "alpha": 1.5,
        "beta": 1.0080065556053466,
        "n": 1
      },
      {
        "state_index": 474,
        "action_index": 23,
        "mu_n": -1.2591491395042056,
        "kappa_n": 1.01,
        "alpha": 1.5,
        "beta": 1.0080065556053466,
        "n": 1
      },
      {
        "state_index": 330,
        "action_index": 3,
        "mu_n": 1.3417947481268335,
        "kappa_n": 1.01,
        "alpha": 1.5,
        "beta": 1.0090920863878088,
        "n": 1
      },
      {
        "state_index": 330,
        "action_index": 17,
        "mu_n": 1.3417947481268335,
        "kappa_n": 1.01,
        "alpha": 1.5,
        "beta": 1.0090920863878088,
        "n": 1
      },
      {
        "state_index": 330,
        "action_index": 18,
        "mu_n": 1.3417947481268335,
        "kappa_n": 1.01,
        "alpha": 1.5,
        "beta": 1.0090920863878088,
        "n": 1
      },
      {
        "state_index": 93,
        "action_index": 2,
        "mu_n": 0.13364265812167606,
        "kappa_n": 1.01,
        "alpha": 1.5,
        "beta": 1.0000901948183527,
        "n": 1
      },
      {
        "state_index": 93,
        "action_index": 11,
        "mu_n": 0.13364265812167606,
        "kappa_n": 1.01,
        "alpha": 1.5,
        "beta": 1.0000901948183527,
        "n": 1
      },
      {
        "state_index": 93,
        "action_index": 18,
        "mu_n": 0.13364265812167606,
        "kappa_n": 1.01,
        "alpha": 1.5,
        "beta": 1.0000901948183527,
        "n": 1
      },
      {
        "state_index": 93,
        "action_index": 19,
        "mu_n": 0.13364265812167606,
        "kappa_n": 1.01,
        "alpha": 1.5,
        "beta": 1.0000901948183527,
        "n": 1
      },
      {
        "state_index": 120,
        "action_index": 8,
        "mu_n": 0.13364265812167606,
        "kappa_n": 1.01,
        "alpha": 1.5,
        "beta": 1.0000901948183527,
        "n": 1
      },
      {
        "state_index": 120,
        "action_index": 9,
        "mu_n": 0.13364265812167606,
        "kappa_n": 1.01,
        "alpha": 1.5,
        "beta": 1.0000901948183527,
        "n": 1
      },
      {
        "state_index": 120,
        "action_index": 19,
        "mu_n": 0.13364265812167606,
        "kappa_n": 1.01,
        "alpha": 1.5,
        "beta": 1.0000901948183527,
        "n": 1
      },
      {
        "state_index": 120,
        "action_index": 20,
        "mu_n": 0.13364265812167606,
        "kappa_n": 1.01,
        "alpha": 1.5,
        "beta": 1.0000901948183527,
        "n": 1
      },
      {
        "state_index": 582,
        "action_index": 0,
        "mu_n": 5.110534678204357,
        "kappa_n": 1.01,
        "alpha": 1.5,
        "beta": 1.131893701720503,
        "n": 1
      },
      {
        "state_index": 582,
        "action_index": 1,
        "mu_n": 5.110534678204357,
        "kappa_n": 1.01,
        "alpha": 1.5,
        "beta": 1.131893701720503,
        "n": 1
      },
      {
        "state_index": 582,
        "action_index": 2,
        "mu_n": 3.4428657779544842,
        "kappa_n": 1.01,
        "alpha": 1.5,
        "beta": 1.0598592900633013,
        "n": 1
      },
      {
        "state_index": 582,
        "action_index": 3,
        "mu_n": 3.86462398077227,
        "kappa_n": 1.01,
        "alpha": 1.5,
        "beta": 1.0754233584894386,
        "n": 1
      },
      {
        "state_index": 582,
        "action_index": 8,
        "mu_n": 5.110534678204357,
        "kappa_n": 1.01,
        "alpha": 1.5,
        "beta": 1.131893701720503,
        "n": 1
      },
      {
        "state_index": 582,
        "action_index": 9,
        "mu_n": 3.4428657779544842,
        "kappa_n": 1.01,
        "alpha": 1.5,
        "beta": 1.0598592900633013,
        "n": 1
      },
      {
        "state_index": 582,
        "action_index": 12,
        "mu_n": 2.7946475021224773,
        "kappa_n": 1.01,
        "alpha": 1.5,
        "beta": 1.039440776038653,
        "n": 1
      },
      {
        "state_index": 582,
        "action_index": 14,
        "mu_n": 1.0154373753910766,
        "kappa_n": 1.01,
        "alpha": 1.5,
        "beta": 1.0052071209698727,
        "n": 1
      },
      {
        "state_index": 582,
        "action_index": 16,
        "mu_n": 2.7946475021224773,
        "kappa_n": 1.01,
        "alpha": 1.5,
        "beta": 1.039440776038653,
        "n": 1
      },
      {
        "state_index": 582,
        "action_index": 17,
        "mu_n": 3.459994463416945,
        "kappa_n": 2.01,
        "alpha": 2.0,
        "beta": 1.0601570974765515,
        "n": 2
      },
      {
        "state_index": 582,
        "action_index": 18,
        "mu_n": -1.6139990241303477,
        "kappa_n": 1.01,
        "alpha": 1.5,
        "beta": 1.0131552138919633,
        "n": 1
      },
      {
        "state_index": 582,
        "action_index": 19,
        "mu_n": 5.110534678204357,
        "kappa_n": 1.01,
        "alpha": 1.5,
        "beta": 1.131893701720503,
        "n": 1
      },
      {
        "state_index": 582,
        "action_index": 20,
        "mu_n": 3.86462398077227,
        "kappa_n": 1.01,
        "alpha": 1.5,
        "beta": 1.0754233584894386,
        "n": 1
      },
      {
        "state_index": 582,
        "action_index": 24,
        "mu_n": 1.0154373753910766,
        "kappa_n": 1.01,
        "alpha": 1.5,
        "beta": 1.0052071209698727,
        "n": 1
      },
      {
        "state_index": 33,
        "action_index": 11,
        "mu_n": 2.4742851470069427,
        "kappa_n": 1.01,
        "alpha": 1.5,
        "beta": 1.0309165392929307,
        "n": 1
      },
      {
        "state_index": 60,
        "action_index": 19,
        "mu_n": 1.293784194817734,
        "kappa_n": 1.01,
        "alpha": 1.5,
        "beta": 1.008453081590939,
        "n": 1
      },
      {
        "state_index": 60,
        "action_index": 23,
        "mu_n": 1.293784194817734,
        "kappa_n": 1.01,
        "alpha": 1.5,
        "beta": 1.008453081590939,
        "n": 1
      },
      {
        "state_index": 528,
        "action_index": 1,
        "mu_n": 7.810830552558838,
        "kappa_n": 1.01,
        "alpha": 1.5,
        "beta": 1.3080958232999724,
        "n": 1
      },
      {
        "state_index": 528,
        "action_index": 5,
        "mu_n": 7.810830552558838,
        "kappa_n": 1.01,
        "alpha": 1.5,
        "beta": 1.3080958232999724,
        "n": 1
      },
      {
        "state_index": 528,
        "action_index": 13,
        "mu_n": 7.849690406054156,
        "kappa_n": 2.01,
        "alpha": 2.0,
        "beta": 1.3096286383412659,
        "n": 2
      },
      {
        "state_index": 528,
        "action_index": 16,
        "mu_n": 7.810830552558838,
        "kappa_n": 1.01,
        "alpha": 1.5,
        "beta": 1.3080958232999724,
        "n": 1
      },
      {
        "state_index": 528,
        "action_index": 23,
        "mu_n": 7.810830552558838,
        "kappa_n": 1.01,
        "alpha": 1.5,
        "beta": 1.3080958232999724,
        "n": 1
      },
      {
        "state_index": 555,
        "action_index": 0,
        "mu_n": 2.7946475021224773,
        "kappa_n": 1.01,
        "alpha": 1.5,
        "beta": 1.039440776038653,
        "n": 1
      },
      {
        "state_index": 555,
        "action_index": 1,
        "mu_n": -2.0831651573109884,
        "kappa_n": 2.01,
        "alpha": 2.0,
        "beta": 25.190582614492996,
        "n": 2
      },
      {
        "state_index": 555,
        "action_index": 2,
        "mu_n": 2.7946475021224773,
        "kappa_n": 1.01,
        "alpha": 1.5,
        "beta": 1.039440776038653,
        "n": 1
      },
      {
        "state_index": 555,
        "action_index": 3,
        "mu_n": 1.885327612192497,
        "kappa_n": 5.01,
        "alpha": 3.5,
        "beta": 91.74188502478165,
        "n": 5
      },
      {
        "state_index": 555,
        "action_index": 4,
        "mu_n": 4.738696633925275,
        "kappa_n": 2.01,
        "alpha": 2.0,
        "beta": 15.53928196362123,
        "n": 2
      },
      {
        "state_index": 555,
        "action_index": 5,
        "mu_n": 2.7946475021224773,
        "kappa_n": 1.01,
        "alpha": 1.5,
        "beta": 1.039440776038653,
        "n": 1
      },
      {
        "state_index": 555,
        "action_index": 6,
        "mu_n": 3.8505138866652544,
        "kappa_n": 2.01,
        "alpha": 2.0,
        "beta": 1.0745029473867949,
        "n": 2
      },
      {
        "state_index": 555,
        "action_index": 7,
        "mu_n": -0.026341826280861944,
        "kappa_n": 3.01,
        "alpha": 2.5,
        "beta": 63.53795955093214,
        "n": 3
      },
      {
        "state_index": 555,
        "action_index": 8,
        "mu_n": 3.8505138866652544,
        "kappa_n": 2.01,
        "alpha": 2.0,
        "beta": 1.0745029473867949,
        "n": 2
      },
      {
        "state_index": 555,
        "action_index": 9,
        "mu_n": -2.4416612709380945,
        "kappa_n": 1.01,
        "alpha": 1.5,
        "beta": 1.0301066342980951,
        "n": 1
      },
      {
        "state_index": 555,
        "action_index": 10,
        "mu_n": 4.299370546214399,
        "kappa_n": 3.01,
        "alpha": 2.5,
        "beta": 29.215247463492553,
        "n": 3
      },
      {
        "state_index": 555,
        "action_index": 11,
        "mu_n": 2.17935287736333,
        "kappa_n": 2.01,
        "alpha": 2.0,
        "beta": 15.619236118118579,
        "n": 2
      },
      {
        "state_index": 555,
        "action_index": 12,
        "mu_n": 5.951127027595985,
        "kappa_n": 1.01,
        "alpha": 1.5,
        "beta": 1.1788503601378462,
        "n": 1
      },
      {
        "state_index": 555,
        "action_index": 13,
        "mu_n": 3.831451936731267,
        "kappa_n": 1.01,
        "alpha": 1.5,
        "beta": 1.074134120914583,
        "n": 1
      },
      {
        "state_index": 555,
        "action_index": 14,
        "mu_n": 4.103552937761396,
        "kappa_n": 4.01,
        "alpha": 3.0,
        "beta": 42.314979486874634,
        "n": 4
      },
      {
        "state_index": 555,
        "action_index": 15,
        "mu_n": -6.940352419147315,
        "kappa_n": 1.01,
        "alpha": 1.5,
        "beta": 1.243250883094918,
        "n": 1
      },
      {
        "state_index": 555,
        "action_index": 16,
        "mu_n": 3.831451936731267,
        "kappa_n": 1.01,
        "alpha": 1.5,
        "beta": 1.074134120914583,
        "n": 1
      },
      {
        "state_index": 555,
        "action_index": 17,
        "mu_n": 1.756965676922761,
        "kappa_n": 2.01,
        "alpha": 2.0,
        "beta": 12.547577445025018,
        "n": 2
      },
      {
        "state_index": 555,
        "action_index": 18,
        "mu_n": 3.459994463416945,
        "kappa_n": 2.01,
        "alpha": 2.0,
        "beta": 1.0601570974765515,
        "n": 2
      },
      {
        "state_index": 555,
        "action_index": 19,
        "mu_n": 2.7946475021224773,
        "kappa_n": 1.01,
        "alpha": 1.5,
        "beta": 1.039440776038653,
        "n": 1
      },
      {
        "state_index": 555,
        "action_index": 20,
        "mu_n": 2.7946475021224773,
        "kappa_n": 1.01,
        "alpha": 1.5,
        "beta": 1.039440776038653,
        "n": 1
      },
      {
        "state_index": 555,
        "action_index": 21,
        "mu_n": 3.831451936731267,
        "kappa_n": 1.01,
        "alpha": 1.5,
        "beta": 1.074134120914583,
        "n": 1
      },
      {
        "state_index": 555,
        "action_index": 22,
        "mu_n": 3.4428657779544842,
        "kappa_n": 1.01,
        "alpha": 1.5,
        "beta": 1.0598592900633013,
        "n": 1
      },
      {
        "state_index": 555,
        "action_index": 23,
        "mu_n": 2.17935287736333,
        "kappa_n": 2.01,
        "alpha": 2.0,
        "beta": 15.619236118118579,
        "n": 2
      },
      {
        "state_index": 555,
        "action_index": 24,
        "mu_n": 6.200933473226387,
        "kappa_n": 2.01,
        "alpha": 2.0,
        "beta": 6.6159134507908455,
        "n": 2
      },
      {
        "state_index": 6,
        "action_index": 2,
        "mu_n": 4.557968538121273,
        "kappa_n": 1.01,
        "alpha": 1.5,
        "beta": 1.104914139832242,
        "n": 1
      },
      {
        "state_index": 6,
        "action_index": 13,
        "mu_n": 4.557968538121273,
        "kappa_n": 1.01,
        "alpha": 1.5,
        "beta": 1.104914139832242,
        "n": 1
      },
      {
        "state_index": 420,
        "action_index": 17,
        "mu_n": 6.470927219977292,
        "kappa_n": 1.01,
        "alpha": 1.5,
        "beta": 1.2114581403855273,
        "n": 1
      },
      {
        "state_index": 420,
        "action_index": 23,
        "mu_n": 6.470927219977292,
        "kappa_n": 1.01,
        "alpha": 1.5,
        "beta": 1.2114581403855273,
        "n": 1
      },
      {
        "state_index": 339,
        "action_index": 6,
        "mu_n": 4.9266314899243895,
        "kappa_n": 2.01,
        "alpha": 2.0,
        "beta": 1.1219652816335108,
        "n": 2
      },
      {
        "state_index": 339,
        "action_index": 12,
        "mu_n": 4.902242225122783,
        "kappa_n": 1.01,
        "alpha": 1.5,
        "beta": 1.1213614931105726,
        "n": 1
      },
      {
        "state_index": 339,
        "action_index": 14,
        "mu_n": 1.571695938279263,
        "kappa_n": 1.01,
        "alpha": 1.5,
        "beta": 1.0124746520181378,
        "n": 1
      },
      {
        "state_index": 339,
        "action_index": 18,
        "mu_n": 4.902242225122783,
        "kappa_n": 1.01,
        "alpha": 1.5,
        "beta": 1.1213614931105726,
        "n": 1
      },
      {
        "state_index": 249,
        "action_index": 14,
        "mu_n": 6.852167335268582,
        "kappa_n": 1.01,
        "alpha": 1.5,
        "beta": 1.2371085958121348,
        "n": 1
      }
    ],
    "episodes": 0,
    "total_reward": 1197.0950582944945,
    "total_observations": 460
  }
}