{
  "metadata": {
    "version": 1,
    "timestamp_ms": 1770635386716,
    "asset": "hyna:HYPE",
    "session_duration_s": 2414.201944344
  },
  "learned_params": {
    "alpha_touch": {
      "name": "alpha_touch",
      "family": "Beta",
      "prior_mean": 0.25,
      "prior_strength": 8.0,
      "posterior_param1": 6.0,
      "posterior_param2": 8.0,
      "n_observations": 6,
      "sum_x": 0.0,
      "sum_x2": 0.0
    },
    "gamma_base": {
      "name": "gamma_base",
      "family": "Gamma",
      "prior_mean": 0.15,
      "prior_strength": 3.0,
      "posterior_param1": 3.0,
      "posterior_param2": 20.0,
      "n_observations": 0,
      "sum_x": 0.0,
      "sum_x2": 0.0
    },
    "spread_floor_bps": {
      "name": "spread_floor_bps",
      "family": "Normal",
      "prior_mean": 5.0,
      "prior_strength": 0.25,
      "posterior_param1": 5.0,
      "posterior_param2": 4.0,
      "n_observations": 0,
      "sum_x": 0.0,
      "sum_x2": 0.0
    },
    "proactive_skew_sensitivity": {
      "name": "proactive_skew_sensitivity",
      "family": "Normal",
      "prior_mean": 2.0,
      "prior_strength": 4.0,
      "posterior_param1": 2.0,
      "posterior_param2": 0.25,
      "n_observations": 0,
      "sum_x": 0.0,
      "sum_x2": 0.0
    },
    "quote_gate_edge_threshold": {
      "name": "quote_gate_edge_threshold",
      "family": "Beta",
      "prior_mean": 0.15,
      "prior_strength": 100.0,
      "posterior_param1": 15.0,
      "posterior_param2": 85.0,
      "n_observations": 0,
      "sum_x": 0.0,
      "sum_x2": 0.0
    },
    "toxic_hour_gamma_mult": {
      "name": "toxic_hour_gamma_mult",
      "family": "LogNormal",
      "prior_mean": 2.0,
      "prior_strength": 3.4064542452769913,
      "posterior_param1": 0.6500583324394191,
      "posterior_param2": 0.08617769624105241,
      "n_observations": 0,
      "sum_x": 0.0,
      "sum_x2": 0.0
    },
    "predictive_bias_sensitivity": {
      "name": "predictive_bias_sensitivity",
      "family": "Normal",
      "prior_mean": 2.0,
      "prior_strength": 1.0,
      "posterior_param1": 2.0,
      "posterior_param2": 1.0,
      "n_observations": 0,
      "sum_x": 0.0,
      "sum_x2": 0.0
    },
    "max_daily_loss_fraction": {
      "name": "max_daily_loss_fraction",
      "family": "Beta",
      "prior_mean": 0.02,
      "prior_strength": 50.0,
      "posterior_param1": 1.0,
      "posterior_param2": 49.0,
      "n_observations": 0,
      "sum_x": 0.0,
      "sum_x2": 0.0
    },
    "max_drawdown": {
      "name": "max_drawdown",
      "family": "Beta",
      "prior_mean": 0.05,
      "prior_strength": 20.0,
      "posterior_param1": 1.0,
      "posterior_param2": 19.0,
      "n_observations": 0,
      "sum_x": 0.0,
      "sum_x2": 0.0
    },
    "cascade_oi_threshold": {
      "name": "cascade_oi_threshold",
      "family": "Beta",
      "prior_mean": 0.02,
      "prior_strength": 100.0,
      "posterior_param1": 2.0,
      "posterior_param2": 98.0,
      "n_observations": 0,
      "sum_x": 0.0,
      "sum_x2": 0.0
    },
    "bocpd_hazard_rate": {
      "name": "bocpd_hazard_rate",
      "family": "Gamma",
      "prior_mean": 0.004,
      "prior_strength": 1.0,
      "posterior_param1": 1.0,
      "posterior_param2": 250.0,
      "n_observations": 0,
      "sum_x": 0.0,
      "sum_x2": 0.0
    },
    "bocpd_threshold": {
      "name": "bocpd_threshold",
      "family": "Beta",
      "prior_mean": 0.7,
      "prior_strength": 10.0,
      "posterior_param1": 7.0,
      "posterior_param2": 3.0000000000000004,
      "n_observations": 0,
      "sum_x": 0.0,
      "sum_x2": 0.0
    },
    "quote_latch_threshold_bps": {
      "name": "quote_latch_threshold_bps",
      "family": "Normal",
      "prior_mean": 2.5,
      "prior_strength": 1.0,
      "posterior_param1": 2.5,
      "posterior_param2": 1.0,
      "n_observations": 0,
      "sum_x": 0.0,
      "sum_x2": 0.0
    },
    "kappa": {
      "name": "kappa",
      "family": "Gamma",
      "prior_mean": 2000.0,
      "prior_strength": 4.0,
      "posterior_param1": 4.0,
      "posterior_param2": 0.002,
      "n_observations": 0,
      "sum_x": 0.0,
      "sum_x2": 0.0
    },
    "hawkes_mu": {
      "name": "hawkes_mu",
      "family": "Gamma",
      "prior_mean": 0.5,
      "prior_strength": 5.0,
      "posterior_param1": 5.0,
      "posterior_param2": 10.0,
      "n_observations": 0,
      "sum_x": 0.0,
      "sum_x2": 0.0
    },
    "hawkes_alpha": {
      "name": "hawkes_alpha",
      "family": "Beta",
      "prior_mean": 0.3,
      "prior_strength": 10.0,
      "posterior_param1": 3.0,
      "posterior_param2": 7.0,
      "n_observations": 0,
      "sum_x": 0.0,
      "sum_x2": 0.0
    },
    "hawkes_beta": {
      "name": "hawkes_beta",
      "family": "Gamma",
      "prior_mean": 0.1,
      "prior_strength": 1.0,
      "posterior_param1": 1.0,
      "posterior_param2": 10.0,
      "n_observations": 0,
      "sum_x": 0.0,
      "sum_x2": 0.0
    },
    "kappa_ewma_alpha": {
      "name": "kappa_ewma_alpha",
      "family": "Beta",
      "prior_mean": 0.9,
      "prior_strength": 100.0,
      "posterior_param1": 90.0,
      "posterior_param2": 9.999999999999998,
      "n_observations": 0,
      "sum_x": 0.0,
      "sum_x2": 0.0
    },
    "kelly_tracker_decay": {
      "name": "kelly_tracker_decay",
      "family": "Beta",
      "prior_mean": 0.99,
      "prior_strength": 100.0,
      "posterior_param1": 99.0,
      "posterior_param2": 1.0000000000000009,
      "n_observations": 0,
      "sum_x": 0.0,
      "sum_x2": 0.0
    },
    "regime_sticky_diagonal": {
      "name": "regime_sticky_diagonal",
      "family": "Beta",
      "prior_mean": 0.95,
      "prior_strength": 100.0,
      "posterior_param1": 95.0,
      "posterior_param2": 5.000000000000004,
      "n_observations": 0,
      "sum_x": 0.0,
      "sum_x2": 0.0
    },
    "kalman_q": {
      "name": "kalman_q",
      "family": "InverseGamma",
      "prior_mean": 1e-8,
      "prior_strength": 20.0,
      "posterior_param1": 10.0,
      "posterior_param2": 9e-8,
      "n_observations": 0,
      "sum_x": 0.0,
      "sum_x2": 0.0
    },
    "kalman_r": {
      "name": "kalman_r",
      "family": "InverseGamma",
      "prior_mean": 2.5e-9,
      "prior_strength": 20.0,
      "posterior_param1": 10.0,
      "posterior_param2": 2.25e-8,
      "n_observations": 0,
      "sum_x": 0.0,
      "sum_x2": 0.0
    },
    "momentum_normalizer_bps": {
      "name": "momentum_normalizer_bps",
      "family": "Gamma",
      "prior_mean": 20.0,
      "prior_strength": 4.0,
      "posterior_param1": 4.0,
      "posterior_param2": 0.2,
      "n_observations": 0,
      "sum_x": 0.0,
      "sum_x2": 0.0
    },
    "depth_spacing_ratio": {
      "name": "depth_spacing_ratio",
      "family": "LogNormal",
      "prior_mean": 1.5,
      "prior_strength": 5.04942884800136,
      "posterior_param1": 0.3858547515315237,
      "posterior_param2": 0.03922071315328133,
      "n_observations": 0,
      "sum_x": 0.0,
      "sum_x2": 0.0
    },
    "fill_probability_width_bps": {
      "name": "fill_probability_width_bps",
      "family": "Normal",
      "prior_mean": 2.0,
      "prior_strength": 4.0,
      "posterior_param1": 2.0,
      "posterior_param2": 0.25,
      "n_observations": 0,
      "sum_x": 0.0,
      "sum_x2": 0.0
    },
    "microprice_decay": {
      "name": "microprice_decay",
      "family": "Beta",
      "prior_mean": 0.999,
      "prior_strength": 1000.0,
      "posterior_param1": 999.0,
      "posterior_param2": 1.0000000000000009,
      "n_observations": 0,
      "sum_x": 0.0,
      "sum_x2": 0.0
    },
    "total_fills_observed": 0
  },
  "pre_fill": {
    "learned_weights": [
      0.3,
      0.25,
      0.25,
      0.1,
      0.1
    ],
    "signal_outcome_sum": [
      0.0,
      0.0,
      0.0,
      0.0,
      0.0
    ],
    "signal_sq_sum": [
      0.21523041141949423,
      0.09616159275174162,
      0.34226844407940704,
      0.175,
      0.25246236957262547
    ],
    "learning_samples": 7,
    "regime_probs": [
      0.1,
      0.7,
      0.15,
      0.05
    ],
    "imbalance_ewma_mean": -0.7591085811748585,
    "imbalance_ewma_var": 2.483418168288242,
    "flow_ewma_mean": 0.3514934309469733,
    "flow_ewma_var": 0.03430284355724191,
    "funding_ewma_mean": 0.0,
    "funding_ewma_var": 0.01490512538247475,
    "regime_trust_prev": 0.7262033988763951,
    "regime_ewma_mean": 0.16602212516477202,
    "regime_ewma_var": 0.03901742151043535,
    "changepoint_ewma_mean": 0.02458853944285381,
    "changepoint_ewma_var": 0.017525573417412375,
    "normalizer_obs_count": 4748
  },
  "enhanced": {
    "learned_weights": [
      0.10780916624275141,
      0.224770274571622,
      0.18497521954276694,
      0.08389368550667373,
      0.07473348733093092,
      0.04086732264938581,
      0.08173464529877161,
      0.05108415331173226,
      0.07891573771501253,
      0.0712163078303529
    ],
    "weight_gradients": [
      0.34947998729275337,
      0.0,
      0.09952835280771127,
      0.019198745254312467,
      0.23734476232837373,
      0.0,
      0.0,
      0.0,
      0.07102205223716344,
      0.003405805811915682
    ],
    "learning_samples": 7,
    "prediction_sum": 3.882411687857645,
    "outcome_sum": 0.0,
    "correct_predictions": 1,
    "total_predictions": 7
  },
  "vol_filter": {
    "sigma_mean": 0.0011153274808010768,
    "sigma_std": 0.00046073100553918074,
    "regime_probs": [
      0.18673450544227393,
      0.48254399984453417,
      0.2658473246473569,
      0.06487417006583453
    ],
    "observation_count": 184
  },
  "regime_hmm": {
    "belief": [
      0.17126059376786928,
      0.8025343212612032,
      0.026046116100818095,
      0.00015896887010945904
    ],
    "transition_counts": [
      [
        0.0,
        0.0,
        0.0,
        0.0
      ],
      [
        0.0,
        0.0,
        0.0,
        0.0
      ],
      [
        0.0,
        0.0,
        0.0,
        0.0
      ],
      [
        0.0,
        0.0,
        0.0,
        0.0
      ]
    ],
    "observation_count": 173,
    "recalibration_count": 0
  },
  "informed_flow": {
    "component_params": [
      {
        "mu_size": -0.6748312265102557,
        "sigma_size": 0.1387502254072091,
        "lambda_0": 0.046551515749623684,
        "alpha": 0.5,
        "beta": 2.0,
        "impact_per_unit": 7.685084126440728,
        "impact_variance": 1.9586135464504792
      },
      {
        "mu_size": 2.509538373284973,
        "sigma_size": 1.4261848217748685,
        "lambda_0": 0.18404002717145604,
        "alpha": 0.1,
        "beta": 5.0,
        "impact_per_unit": 0.011209670708843439,
        "impact_variance": 26.63405771533834
      },
      {
        "mu_size": -0.0916636927929545,
        "sigma_size": 0.9032915587383702,
        "lambda_0": 0.08259348890319497,
        "alpha": 0.8,
        "beta": 1.0,
        "impact_per_unit": -10.0,
        "impact_variance": 100.0
      }
    ],
    "mixing_weights": [
      0.26410221681587726,
      0.3824520056228469,
      0.35344577756127593
    ],
    "observation_count": 287
  },
  "fill_rate": {
    "lambda_0_mean": 0.09291741410147582,
    "lambda_0_variance": 0.001919176919108447,
    "lambda_0_n_obs": 16.382980873619093,
    "delta_char_mean": 10.0,
    "delta_char_variance": 20.994333672461345,
    "delta_char_n_obs": 4.763189990219688,
    "observation_count": 7
  },
  "kappa_own": {
    "prior_alpha": 5.0,
    "prior_beta": 0.0033333333333333335,
    "observation_count": 6,
    "sum_distances": 0.00006,
    "sum_sq_distances": 6.000000000000002e-10,
    "kappa_posterior_mean": 3241.650294695481
  },
  "kappa_bid": {
    "prior_alpha": 5.0,
    "prior_beta": 0.0033333333333333335,
    "observation_count": 1,
    "sum_distances": 0.00001,
    "sum_sq_distances": 1.0000000000000002e-10,
    "kappa_posterior_mean": 1794.616151545364
  },
  "kappa_ask": {
    "prior_alpha": 5.0,
    "prior_beta": 0.0033333333333333335,
    "observation_count": 6,
    "sum_distances": 0.00006,
    "sum_sq_distances": 6.000000000000002e-10,
    "kappa_posterior_mean": 3241.650294695481
  },
  "momentum": {
    "continuation_by_magnitude": [
      0.521180693340664,
      0.483365702531505,
      0.6193713405281654,
      0.41805000000000003,
      0.55,
      0.5,
      0.5,
      0.5,
      0.5,
      0.5
    ],
    "counts_by_magnitude": [
      82,
      55,
      19,
      4,
      1,
      0,
      0,
      0,
      0,
      0
    ],
    "prior_continuation": 0.5
  },
  "kelly_tracker": {
    "ewma_wins": 5.494864380082568,
    "n_wins": 6,
    "ewma_losses": 3.0,
    "n_losses": 0,
    "decay": 0.99
  },
  "ensemble_weights": {
    "model_weights": [
      0.9090909090909091,
      0.045454545454545456,
      0.045454545454545456
    ],
    "total_updates": 6
  },
  "rl_q_table": {
    "q_entries": [
      {
        "state_index": 333,
        "action_index": 10,
        "mu_n": 19.21263891188772,
        "kappa_n": 1.01,
        "alpha": 1.5,
        "beta": 2.8640837444908396,
        "n": 1
      },
      {
        "state_index": 333,
        "action_index": 11,
        "mu_n": -0.08298529292684186,
        "kappa_n": 1.01,
        "alpha": 1.5,
        "beta": 1.000034777122153,
        "n": 1
      },
      {
        "state_index": 279,
        "action_index": 1,
        "mu_n": 1.8822964797353194,
        "kappa_n": 1.01,
        "alpha": 1.5,
        "beta": 1.0178923521900012,
        "n": 1
      },
      {
        "state_index": 200,
        "action_index": 12,
        "mu_n": 34.36401538110288,
        "kappa_n": 3.01,
        "alpha": 2.5,
        "beta": 196.33678471568405,
        "n": 3
      },
      {
        "state_index": 414,
        "action_index": 9,
        "mu_n": 19.21263891188772,
        "kappa_n": 1.01,
        "alpha": 1.5,
        "beta": 2.8640837444908396,
        "n": 1
      },
      {
        "state_index": 414,
        "action_index": 11,
        "mu_n": 19.21263891188772,
        "kappa_n": 1.01,
        "alpha": 1.5,
        "beta": 2.8640837444908396,
        "n": 1
      },
      {
        "state_index": 270,
        "action_index": 8,
        "mu_n": 19.21263891188772,
        "kappa_n": 1.01,
        "alpha": 1.5,
        "beta": 2.8640837444908396,
        "n": 1
      },
      {
        "state_index": 378,
        "action_index": 6,
        "mu_n": 3.8282477633850354,
        "kappa_n": 1.01,
        "alpha": 1.5,
        "beta": 1.0740101787362055,
        "n": 1
      }
    ],
    "episodes": 0,
    "total_reward": 141.5171916467416,
    "total_observations": 10
  }
}